{"resultCount": 2, "results": [{"wrapperType": "track", "kind": "podcast", "collectionId": 1554647147, "trackId": 1554647147, "artistName": "Bornó de Cores", "collectionName": "Bornó de Cores", "trackName": "Bornó de Cores", "collectionCensoredName": "Bornó de Cores", "trackCensoredName": "Bornó de Cores", "collectionViewUrl": "https://podcasts.apple.com/ng/podcast/born%C3%B3-de-cores/id1554647147?uo=4", "feedUrl": "https://anchor.fm/s/4db31fbc/podcast/rss", "trackViewUrl": "https://podcasts.apple.com/ng/podcast/born%C3%B3-de-cores/id1554647147?uo=4", "artworkUrl30": "https://is1-ssl.mzstatic.com/image/thumb/Podcasts124/v4/e8/19/aa/e819aafc-de7d-149a-4a16-0ad001d23934/mza_11316809360798103708.jpg/30x30bb.jpg", "artworkUrl60": "https://is1-ssl.mzstatic.com/image/thumb/Podcasts124/v4/e8/19/aa/e819aafc-de7d-149a-4a16-0ad001d23934/mza_11316809360798103708.jpg/60x60bb.jpg", "artworkUrl100": "https://is1-ssl.mzstatic.com/image/thumb/Podcasts124/v4/e8/19/aa/e819aafc-de7d-149a-4a16-0ad001d23934/mza_11316809360798103708.jpg/100x100bb.jpg", "collectionPrice": 0.0, "trackPrice": 0.0, "collectionHdPrice": 0, "releaseDate": "2021-02-20T12:39:00Z", "collectionExplicitness": "notExplicit", "trackExplicitness": "cleaned", "trackCount": 3, "trackTimeMillis": 912, "country": "NGA", "currency": "NGN", "primaryGenreName": "Music Interviews", "contentAdvisoryRating": "Clean", "artworkUrl600": "https://is1-ssl.mzstatic.com/image/thumb/Podcasts124/v4/e8/19/aa/e819aafc-de7d-149a-4a16-0ad001d23934/mza_11316809360798103708.jpg/600x600bb.jpg", "genreIds": ["1525", "26", "1310"], "genres": ["Music Interviews", "Podcasts", "Music"]}, {"wrapperType": "track", "kind": "podcast", "collectionId": 1576634219, "trackId": 1576634219, "artistName": "Awe", "collectionName": "Borno Podcast", "trackName": "Borno Podcast", "collectionCensoredName": "Borno Podcast", "trackCensoredName": "Borno Podcast", "collectionViewUrl": "https://podcasts.apple.com/ng/podcast/borno-podcast/id1576634219?uo=4", "feedUrl": "https://anchor.fm/s/64013ad8/podcast/rss", "trackViewUrl": "https://podcasts.apple.com/ng/podcast/borno-podcast/id1576634219?uo=4", "artworkUrl30": "https://is1-ssl.mzstatic.com/image/thumb/Podcasts125/v4/33/01/5f/33015f86-78b6-4349-ebc4-088ea0df4865/mza_17955073707561335588.jpg/30x30bb.jpg", "artworkUrl60": "https://is1-ssl.mzstatic.com/image/thumb/Podcasts125/v4/33/01/5f/33015f86-78b6-4349-ebc4-088ea0df4865/mza_17955073707561335588.jpg/60x60bb.jpg", "artworkUrl100": "https://is1-ssl.mzstatic.com/image/thumb/Podcasts125/v4/33/01/5f/33015f86-78b6-4349-ebc4-088ea0df4865/mza_17955073707561335588.jpg/100x100bb.jpg", "collectionPrice": 0.0, "trackPrice": 0.0, "collectionHdPrice": 0, "releaseDate": "2021-07-19T07:04:00Z", "collectionExplicitness": "notExplicit", "trackExplicitness": "cleaned", "trackCount": 5, "trackTimeMillis": 66, "country": "NGA", "currency": "NGN", "primaryGenreName": "Science Fiction", "contentAdvisoryRating": "Clean", "artworkUrl600": "https://is1-ssl.mzstatic.com/image/thumb/Podcasts125/v4/33/01/5f/33015f86-78b6-4349-ebc4-088ea0df4865/mza_17955073707561335588.jpg/600x600bb.jpg", "genreIds": ["1485", "26", "1483"], "genres": ["Science Fiction", "Podcasts", "Fiction"]}]}