{"resultCount": 50, "results": [{"wrapperType": "track", "kind": "podcast", "artistId": 1280665347, "collectionId": 417986961, "trackId": 417986961, "artistName": "Ludwig-Maximilians-Universität München", "collectionName": "Fakultät für Biologie - Digitale Hochschulschriften der LMU - Teil 04/06", "trackName": "Fakultät für Biologie - Digitale Hochschulschriften der LMU - Teil 04/06", "collectionCensoredName": "Fakultät für Biologie - Digitale Hochschulschriften der LMU - Teil 04/06", "trackCensoredName": "Fakultät für Biologie - Digitale Hochschulschriften der LMU - Teil 04/06", "artistViewUrl": "https://podcasts.apple.com/id/artist/ludwig-maximilians-universit%C3%A4t-m%C3%BCnchen/1280665347?uo=4", "collectionViewUrl": "https://podcasts.apple.com/id/podcast/fakult%C3%A4t-f%C3%BCr-biologie-digitale-hochschulschriften-der/id417986961?uo=4", "feedUrl": "http://xserve04.itunes.uni-muenchen.de/itunesu/Forschung/UBeMedien/EDOC/Biologie_004.rss", "trackViewUrl": "https://podcasts.apple.com/id/podcast/fakult%C3%A4t-f%C3%BCr-biologie-digitale-hochschulschriften-der/id417986961?uo=4", "artworkUrl30": "https://is1-ssl.mzstatic.com/image/thumb/Podcasts125/v4/a0/40/58/a0405869-d71d-75ec-9077-e46f4c6f06a7/mza_5191309158867823180.jpg/30x30bb.jpg", "artworkUrl60": "https://is1-ssl.mzstatic.com/image/thumb/Podcasts125/v4/a0/40/58/a0405869-d71d-75ec-9077-e46f4c6f06a7/mza_5191309158867823180.jpg/60x60bb.jpg", "artworkUrl100": "https://is1-ssl.mzstatic.com/image/thumb/Podcasts125/v4/a0/40/58/a0405869-d71d-75ec-9077-e46f4c6f06a7/mza_5191309158867823180.jpg/100x100bb.jpg", "collectionPrice": 0.0, "trackPrice": 0.0, "collectionHdPrice": 0, "releaseDate": "2012-07-31T11:00:00Z", "collectionExplicitness": "notExplicit", "trackExplicitness": "cleaned", "trackCount": 250, "trackTimeMillis": 0, "country": "IDN", "currency": "IDR", "primaryGenreName": "Education", "contentAdvisoryRating": "Clean", "artworkUrl600": "https://is1-ssl.mzstatic.com/image/thumb/Podcasts125/v4/a0/40/58/a0405869-d71d-75ec-9077-e46f4c6f06a7/mza_5191309158867823180.jpg/600x600bb.jpg", "genreIds": ["1304", "26", "1533"], "genres": ["Education", "Podcasts", "Science"]}, {"wrapperType": "track", "kind": "podcast", "collectionId": 1467904073, "trackId": 1467904073, "artistName": "Bingkai Karya", "collectionName": "Bingkai Suara", "trackName": "Bingkai Suara", "collectionCensoredName": "Bingkai Suara", "trackCensoredName": "Bingkai Suara", "collectionViewUrl": "https://podcasts.apple.com/id/podcast/bingkai-suara/id1467904073?uo=4", "feedUrl": "https://anchor.fm/s/bee199c/podcast/rss", "trackViewUrl": "https://podcasts.apple.com/id/podcast/bingkai-suara/id1467904073?uo=4", "artworkUrl30": "https://is1-ssl.mzstatic.com/image/thumb/Podcasts211/v4/2f/de/2e/2fde2e98-26a8-a9d0-ae52-ce48868c9d62/mza_6967797068495308085.jpg/30x30bb.jpg", "artworkUrl60": "https://is1-ssl.mzstatic.com/image/thumb/Podcasts211/v4/2f/de/2e/2fde2e98-26a8-a9d0-ae52-ce48868c9d62/mza_6967797068495308085.jpg/60x60bb.jpg", "artworkUrl100": "https://is1-ssl.mzstatic.com/image/thumb/Podcasts211/v4/2f/de/2e/2fde2e98-26a8-a9d0-ae52-ce48868c9d62/mza_6967797068495308085.jpg/100x100bb.jpg", "collectionPrice": 0.0, "trackPrice": 0.0, "collectionHdPrice": 0, "releaseDate": "2026-06-28T14:53:00Z", "collectionExplicitness": "notExplicit", "trackExplicitness": "cleaned", "trackCount": 855, "trackTimeMillis": 324, "country": "IDN", "currency": "IDR", "primaryGenreName": "Entertainment News", "contentAdvisoryRating": "Clean", "artworkUrl600": "https://is1-ssl.mzstatic.com/image/thumb/Podcasts211/v4/2f/de/2e/2fde2e98-26a8-a9d0-ae52-ce48868c9d62/mza_6967797068495308085.jpg/600x600bb.jpg", "genreIds": ["1531", "26", "1489"], "genres": ["Entertainment News", "Podcasts", "News"]}, {"wrapperType": "track", "kind": "podcast", "collectionId": 1504484631, "trackId": 1504484631, "artistName": "Animalia", "collectionName": "Animalia", "trackName": "Animalia", "collectionCensoredName": "Animalia", "trackCensoredName": "Animalia", "collectionViewUrl": "https://podcasts.apple.com/id/podcast/animalia/id1504484631?uo=4", "feedUrl": "https://anchor.fm/s/174c47dc/podcast/rss", "trackViewUrl": "https://podcasts.apple.com/id/podcast/animalia/id1504484631?uo=4", "artworkUrl30": "https://is1-ssl.mzstatic.com/image/thumb/Podcasts125/v4/f7/22/90/f72290df-6cb9-13f1-c302-532a92f1203e/mza_434975287674386443.jpg/30x30bb.jpg", "artworkUrl60": "https://is1-ssl.mzstatic.com/image/thumb/Podcasts125/v4/f7/22/90/f72290df-6cb9-13f1-c302-532a92f1203e/mza_434975287674386443.jpg/60x60bb.jpg", "artworkUrl100": "https://is1-ssl.mzstatic.com/image/thumb/Podcasts125/v4/f7/22/90/f72290df-6cb9-13f1-c302-532a92f1203e/mza_434975287674386443.jpg/100x100bb.jpg", "collectionPrice": 0.0, "trackPrice": 0.0, "collectionHdPrice": 0, "releaseDate": "2022-09-02T15:58:00Z", "collectionExplicitness": "notExplicit", "trackExplicitness": "cleaned", "trackCount": 88, "trackTimeMillis": 3277, "country": "IDN", "currency": "IDR", "primaryGenreName": "Earth Sciences", "contentAdvisoryRating": "Clean", "artworkUrl600": "https://is1-ssl.mzstatic.com/image/thumb/Podcasts125/v4/f7/22/90/f72290df-6cb9-13f1-c302-532a92f1203e/mza_434975287674386443.jpg/600x600bb.jpg", "genreIds": ["1540", "26", "1533"], "genres": ["Earth Sciences", "Podcasts", "Science"]}, {"wrapperType": "track", "kind": "podcast", "collectionId": 1031451800, "trackId": 1031451800, "artistName": "Talking Indonesia", "collectionName": "Talking Indonesia", "trackName": "Talking Indonesia", "collectionCensoredName": "Talking Indonesia", "trackCensoredName": "Talking Indonesia", "collectionViewUrl": "https://podcasts.apple.com/id/podcast/talking-indonesia/id1031451800?uo=4", "feedUrl": "https://feeds.soundcloud.com/users/soundcloud:users:165729885/sounds.rss", "trackViewUrl": "https://podcasts.apple.com/id/podcast/talking-indonesia/id1031451800?uo=4", "artworkUrl30": "https://is1-ssl.mzstatic.com/image/thumb/Podcasts62/v4/f4/3e/9f/f43e9fa6-5b59-beab-619c-6792d28c4e37/mza_8947974322047714479.jpg/30x30bb.jpg", "artworkUrl60": "https://is1-ssl.mzstatic.com/image/thumb/Podcasts62/v4/f4/3e/9f/f43e9fa6-5b59-beab-619c-6792d28c4e37/mza_8947974322047714479.jpg/60x60bb.jpg", "artworkUrl100": "https://is1-ssl.mzstatic.com/image/thumb/Podcasts62/v4/f4/3e/9f/f43e9fa6-5b59-beab-619c-6792d28c4e37/mza_8947974322047714479.jpg/100x100bb.jpg", "collectionPrice": 0.0, "trackPrice": 0.0, "collectionHdPrice": 0, "releaseDate": "2026-07-01T15:21:00Z", "collectionExplicitness": "notExplicit", "trackExplicitness": "cleaned", "trackCount": 291, "trackTimeMillis": 2102, "country": "IDN", "currency": "IDR", "primaryGenreName": "News", "contentAdvisoryRating": "Clean", "artworkUrl600": "https://is1-ssl.mzstatic.com/image/thumb/Podcasts62/v4/f4/3e/9f/f43e9fa6-5b59-beab-619c-6792d28c4e37/mza_8947974322047714479.jpg/600x600bb.jpg", "genreIds": ["1489", "26"], "genres": ["News", "Podcasts"]}, {"wrapperType": "track", "kind": "podcast", "collectionId": 1753035778, "trackId": 1753035778, "artistName": "focusIR", "collectionName": "focusIR (Share Views)", "trackName": "focusIR (Share Views)", "collectionCensoredName": "focusIR (Share Views)", "trackCensoredName": "focusIR (Share Views)", "collectionViewUrl": "https://podcasts.apple.com/id/podcast/focusir-share-views/id1753035778?uo=4", "feedUrl": "https://anchor.fm/s/ee0c0eb0/podcast/rss", "trackViewUrl": "https://podcasts.apple.com/id/podcast/focusir-share-views/id1753035778?uo=4", "artworkUrl30": "https://is1-ssl.mzstatic.com/image/thumb/Podcasts221/v4/93/47/9c/93479c23-0dd3-32ad-ffd8-276a759cbe38/mza_10942882628059124765.jpg/30x30bb.jpg", "artworkUrl60": "https://is1-ssl.mzstatic.com/image/thumb/Podcasts221/v4/93/47/9c/93479c23-0dd3-32ad-ffd8-276a759cbe38/mza_10942882628059124765.jpg/60x60bb.jpg", "artworkUrl100": "https://is1-ssl.mzstatic.com/image/thumb/Podcasts221/v4/93/47/9c/93479c23-0dd3-32ad-ffd8-276a759cbe38/mza_10942882628059124765.jpg/100x100bb.jpg", "collectionPrice": 0.0, "trackPrice": 0.0, "collectionHdPrice": 0, "releaseDate": "2025-05-07T11:25:00Z", "collectionExplicitness": "notExplicit", "trackExplicitness": "cleaned", "trackCount": 121, "trackTimeMillis": 719, "country": "IDN", "currency": "IDR", "primaryGenreName": "Investing", "contentAdvisoryRating": "Clean", "artworkUrl600": "https://is1-ssl.mzstatic.com/image/thumb/Podcasts221/v4/93/47/9c/93479c23-0dd3-32ad-ffd8-276a759cbe38/mza_10942882628059124765.jpg/600x600bb.jpg", "genreIds": ["1412", "26", "1321"], "genres": ["Investing", "Podcasts", "Business"]}, {"wrapperType": "track", "kind": "podcast", "collectionId": 1471581521, "trackId": 1471581521, "artistName": "Bret Weinstein & Heather Heying", "collectionName": "DarkHorse Podcast", "trackName": "DarkHorse Podcast", "collectionCensoredName": "DarkHorse Podcast", "trackCensoredName": "DarkHorse Podcast", "collectionViewUrl": "https://podcasts.apple.com/id/podcast/darkhorse-podcast/id1471581521?uo=4", "feedUrl": "https://rss.buzzsprout.com/424075.rss", "trackViewUrl": "https://podcasts.apple.com/id/podcast/darkhorse-podcast/id1471581521?uo=4", "artworkUrl30": "https://is1-ssl.mzstatic.com/image/thumb/Podcasts211/v4/70/fc/69/70fc69dc-2b93-9d06-d1df-5556aec6515c/mza_3075224734357125200.jpg/30x30bb.jpg", "artworkUrl60": "https://is1-ssl.mzstatic.com/image/thumb/Podcasts211/v4/70/fc/69/70fc69dc-2b93-9d06-d1df-5556aec6515c/mza_3075224734357125200.jpg/60x60bb.jpg", "artworkUrl100": "https://is1-ssl.mzstatic.com/image/thumb/Podcasts211/v4/70/fc/69/70fc69dc-2b93-9d06-d1df-5556aec6515c/mza_3075224734357125200.jpg/100x100bb.jpg", "collectionPrice": 0.0, "trackPrice": 0.0, "collectionHdPrice": 0, "releaseDate": "2026-07-08T20:00:00Z", "collectionExplicitness": "notExplicit", "trackExplicitness": "cleaned", "trackCount": 477, "trackTimeMillis": 6204, "country": "IDN", "currency": "IDR", "primaryGenreName": "Natural Sciences", "contentAdvisoryRating": "Clean", "artworkUrl600": "https://is1-ssl.mzstatic.com/image/thumb/Podcasts211/v4/70/fc/69/70fc69dc-2b93-9d06-d1df-5556aec6515c/mza_3075224734357125200.jpg/600x600bb.jpg", "genreIds": ["1534", "26", "1533", "1324"], "genres": ["Natural Sciences", "Podcasts", "Science", "Society & Culture"]}, {"wrapperType": "track", "kind": "podcast", "collectionId": 1393913985, "trackId": 1393913985, "artistName": "The Straits Times", "collectionName": "The Straits Times Podcasts", "trackName": "The Straits Times Podcasts", "collectionCensoredName": "The Straits Times Podcasts", "trackCensoredName": "The Straits Times Podcasts", "collectionViewUrl": "https://podcasts.apple.com/id/podcast/the-straits-times-podcasts/id1393913985?uo=4", "feedUrl": "https://www.omnycontent.com/d/playlist/d9486183-3dd4-4ad6-aebe-a4c1008455d5/03fcbf77-09e8-4cb2-88aa-a8e4008b3e9b/58c27497-cc2d-4f57-8d8c-a8e4008b7584/podcast.rss", "trackViewUrl": "https://podcasts.apple.com/id/podcast/the-straits-times-podcasts/id1393913985?uo=4", "artworkUrl30": "https://is1-ssl.mzstatic.com/image/thumb/Podcasts126/v4/8d/a0/d7/8da0d797-6e6a-cd36-b1cd-f850f7276bce/mza_8283336387026988086.jpg/30x30bb.jpg", "artworkUrl60": "https://is1-ssl.mzstatic.com/image/thumb/Podcasts126/v4/8d/a0/d7/8da0d797-6e6a-cd36-b1cd-f850f7276bce/mza_8283336387026988086.jpg/60x60bb.jpg", "artworkUrl100": "https://is1-ssl.mzstatic.com/image/thumb/Podcasts126/v4/8d/a0/d7/8da0d797-6e6a-cd36-b1cd-f850f7276bce/mza_8283336387026988086.jpg/100x100bb.jpg", "collectionPrice": 0.0, "trackPrice": 0.0, "collectionHdPrice": 0, "releaseDate": "2026-07-09T16:00:00Z", "collectionExplicitness": "notExplicit", "trackExplicitness": "cleaned", "trackCount": 2000, "trackTimeMillis": 1282, "country": "IDN", "currency": "IDR", "primaryGenreName": "News Commentary", "contentAdvisoryRating": "Clean", "artworkUrl600": "https://is1-ssl.mzstatic.com/image/thumb/Podcasts126/v4/8d/a0/d7/8da0d797-6e6a-cd36-b1cd-f850f7276bce/mza_8283336387026988086.jpg/600x600bb.jpg", "genreIds": ["1530", "26", "1489", "1527"], "genres": ["News Commentary", "Podcasts", "News", "Politics"]}, {"wrapperType": "track", "kind": "podcast", "collectionId": 1612704797, "trackId": 1612704797, "artistName": "Innovation Forum", "collectionName": "Sustainable Business Podcast by Innovation Forum", "trackName": "Sustainable Business Podcast by Innovation Forum", "collectionCensoredName": "Sustainable Business Podcast by Innovation Forum", "trackCensoredName": "Sustainable Business Podcast by Innovation Forum", "collectionViewUrl": "https://podcasts.apple.com/id/podcast/sustainable-business-podcast-by-innovation-forum/id1612704797?uo=4", "feedUrl": "https://feed.podbean.com/innoforum/feed.xml", "trackViewUrl": "https://podcasts.apple.com/id/podcast/sustainable-business-podcast-by-innovation-forum/id1612704797?uo=4", "artworkUrl30": "https://is1-ssl.mzstatic.com/image/thumb/Podcasts126/v4/fa/7f/75/fa7f7588-5aef-a2ed-046f-87d763b8d2e5/mza_12839723503516386968.png/30x30bb.jpg", "artworkUrl60": "https://is1-ssl.mzstatic.com/image/thumb/Podcasts126/v4/fa/7f/75/fa7f7588-5aef-a2ed-046f-87d763b8d2e5/mza_12839723503516386968.png/60x60bb.jpg", "artworkUrl100": "https://is1-ssl.mzstatic.com/image/thumb/Podcasts126/v4/fa/7f/75/fa7f7588-5aef-a2ed-046f-87d763b8d2e5/mza_12839723503516386968.png/100x100bb.jpg", "collectionPrice": 0.0, "trackPrice": 0.0, "collectionHdPrice": 0, "releaseDate": "2026-07-07T14:12:00Z", "collectionExplicitness": "notExplicit", "trackExplicitness": "cleaned", "trackCount": 995, "trackTimeMillis": 336, "country": "IDN", "currency": "IDR", "primaryGenreName": "Business", "contentAdvisoryRating": "Clean", "artworkUrl600": "https://is1-ssl.mzstatic.com/image/thumb/Podcasts126/v4/fa/7f/75/fa7f7588-5aef-a2ed-046f-87d763b8d2e5/mza_12839723503516386968.png/600x600bb.jpg", "genreIds": ["1321", "26"], "genres": ["Business", "Podcasts"]}, {"wrapperType": "track", "kind": "podcast", "collectionId": 1467876820, "trackId": 1467876820, "artistName": "The Straits Times", "collectionName": "Green Pulse", "trackName": "Green Pulse", "collectionCensoredName": "Green Pulse", "trackCensoredName": "Green Pulse", "collectionViewUrl": "https://podcasts.apple.com/id/podcast/green-pulse/id1467876820?uo=4", "feedUrl": "https://www.omnycontent.com/d/playlist/d9486183-3dd4-4ad6-aebe-a4c1008455d5/3bdcca65-ee0c-4e26-8782-abdb0017cbf2/b97b27d0-118e-4464-b60f-abdb0017cbf2/podcast.rss", "trackViewUrl": "https://podcasts.apple.com/id/podcast/green-pulse/id1467876820?uo=4", "artworkUrl30": "https://is1-ssl.mzstatic.com/image/thumb/Podcasts221/v4/bb/c5/8f/bbc58fae-6fb2-836d-c05a-ab3dd68e8c49/mza_14170471678515547578.jpg/30x30bb.jpg", "artworkUrl60": "https://is1-ssl.mzstatic.com/image/thumb/Podcasts221/v4/bb/c5/8f/bbc58fae-6fb2-836d-c05a-ab3dd68e8c49/mza_14170471678515547578.jpg/60x60bb.jpg", "artworkUrl100": "https://is1-ssl.mzstatic.com/image/thumb/Podcasts221/v4/bb/c5/8f/bbc58fae-6fb2-836d-c05a-ab3dd68e8c49/mza_14170471678515547578.jpg/100x100bb.jpg", "collectionPrice": 0.0, "trackPrice": 0.0, "collectionHdPrice": 0, "releaseDate": "2026-04-06T16:00:00Z", "collectionExplicitness": "notExplicit", "trackExplicitness": "cleaned", "trackCount": 176, "trackTimeMillis": 1657, "country": "IDN", "currency": "IDR", "primaryGenreName": "Nature", "contentAdvisoryRating": "Clean", "artworkUrl600": "https://is1-ssl.mzstatic.com/image/thumb/Podcasts221/v4/bb/c5/8f/bbc58fae-6fb2-836d-c05a-ab3dd68e8c49/mza_14170471678515547578.jpg/600x600bb.jpg", "genreIds": ["1537", "26", "1533", "1534"], "genres": ["Nature", "Podcasts", "Science", "Natural Sciences"]}, {"wrapperType": "track", "kind": "podcast", "collectionId": 1853613817, "trackId": 1853613817, "artistName": "Innovation Forum", "collectionName": "Sustainable Business Podcast by Innovation Forum", "trackName": "Sustainable Business Podcast by Innovation Forum", "collectionCensoredName": "Sustainable Business Podcast by Innovation Forum", "trackCensoredName": "Sustainable Business Podcast by Innovation Forum", "collectionViewUrl": "https://podcasts.apple.com/id/podcast/sustainable-business-podcast-by-innovation-forum/id1853613817?uo=4", "feedUrl": "https://feed.podbean.com/innoforum/feed.xml", "trackViewUrl": "https://podcasts.apple.com/id/podcast/sustainable-business-podcast-by-innovation-forum/id1853613817?uo=4", "artworkUrl30": "https://is1-ssl.mzstatic.com/image/thumb/Podcasts211/v4/66/c5/54/66c554f4-0367-9d63-9e06-016f29461b14/mza_6408832356804906648.png/30x30bb.jpg", "artworkUrl60": "https://is1-ssl.mzstatic.com/image/thumb/Podcasts211/v4/66/c5/54/66c554f4-0367-9d63-9e06-016f29461b14/mza_6408832356804906648.png/60x60bb.jpg", "artworkUrl100": "https://is1-ssl.mzstatic.com/image/thumb/Podcasts211/v4/66/c5/54/66c554f4-0367-9d63-9e06-016f29461b14/mza_6408832356804906648.png/100x100bb.jpg", "collectionPrice": 0.0, "trackPrice": 0.0, "collectionHdPrice": 0, "releaseDate": "2026-07-07T15:33:00Z", "collectionExplicitness": "notExplicit", "trackExplicitness": "cleaned", "trackCount": 998, "trackTimeMillis": 1278, "country": "IDN", "currency": "IDR", "primaryGenreName": "Business", "contentAdvisoryRating": "Clean", "artworkUrl600": "https://is1-ssl.mzstatic.com/image/thumb/Podcasts211/v4/66/c5/54/66c554f4-0367-9d63-9e06-016f29461b14/mza_6408832356804906648.png/600x600bb.jpg", "genreIds": ["1321", "26"], "genres": ["Business", "Podcasts"]}, {"wrapperType": "track", "kind": "podcast", "collectionId": 1685145611, "trackId": 1685145611, "artistName": "BFM Media", "collectionName": "The Daily Digest", "trackName": "The Daily Digest", "collectionCensoredName": "The Daily Digest", "trackCensoredName": "The Daily Digest", "collectionViewUrl": "https://podcasts.apple.com/id/podcast/the-daily-digest/id1685145611?uo=4", "feedUrl": "https://www.omnycontent.com/d/playlist/de62ff84-6498-49d0-a266-a9d50120c712/9f6f92cc-0dba-4bcf-a5f9-ab090057cc51/48b3b2e6-a553-4284-a603-ab090057cc5b/podcast.rss", "trackViewUrl": "https://podcasts.apple.com/id/podcast/the-daily-digest/id1685145611?uo=4", "artworkUrl30": "https://is1-ssl.mzstatic.com/image/thumb/Podcasts116/v4/09/a8/cc/09a8ccc0-debe-5ed8-60d1-b835a6b00520/mza_1589233479666995995.jpg/30x30bb.jpg", "artworkUrl60": "https://is1-ssl.mzstatic.com/image/thumb/Podcasts116/v4/09/a8/cc/09a8ccc0-debe-5ed8-60d1-b835a6b00520/mza_1589233479666995995.jpg/60x60bb.jpg", "artworkUrl100": "https://is1-ssl.mzstatic.com/image/thumb/Podcasts116/v4/09/a8/cc/09a8ccc0-debe-5ed8-60d1-b835a6b00520/mza_1589233479666995995.jpg/100x100bb.jpg", "collectionPrice": 0.0, "trackPrice": 0.0, "collectionHdPrice": 0, "releaseDate": "2021-04-30T06:13:00Z", "collectionExplicitness": "notExplicit", "trackExplicitness": "cleaned", "trackCount": 1010, "trackTimeMillis": 2120, "country": "IDN", "currency": "IDR", "primaryGenreName": "Health & Fitness", "contentAdvisoryRating": "Clean", "artworkUrl600": "https://is1-ssl.mzstatic.com/image/thumb/Podcasts116/v4/09/a8/cc/09a8ccc0-debe-5ed8-60d1-b835a6b00520/mza_1589233479666995995.jpg/600x600bb.jpg", "genreIds": ["1512", "26", "1324"], "genres": ["Health & Fitness", "Podcasts", "Society & Culture"]}, {"wrapperType": "track", "kind": "podcast", "collectionId": 1510292777, "trackId": 1510292777, "artistName": "Ethan Brown", "collectionName": "The Sweaty Penguin", "trackName": "The Sweaty Penguin", "collectionCensoredName": "The Sweaty Penguin", "trackCensoredName": "The Sweaty Penguin", "collectionViewUrl": "https://podcasts.apple.com/id/podcast/the-sweaty-penguin/id1510292777?uo=4", "feedUrl": "https://anchor.fm/s/1d786e38/podcast/rss", "trackViewUrl": "https://podcasts.apple.com/id/podcast/the-sweaty-penguin/id1510292777?uo=4", "artworkUrl30": "https://is1-ssl.mzstatic.com/image/thumb/Podcasts114/v4/1c/9a/66/1c9a66eb-dd26-d58f-3353-6fb18b434273/mza_510582858671591461.jpg/30x30bb.jpg", "artworkUrl60": "https://is1-ssl.mzstatic.com/image/thumb/Podcasts114/v4/1c/9a/66/1c9a66eb-dd26-d58f-3353-6fb18b434273/mza_510582858671591461.jpg/60x60bb.jpg", "artworkUrl100": "https://is1-ssl.mzstatic.com/image/thumb/Podcasts114/v4/1c/9a/66/1c9a66eb-dd26-d58f-3353-6fb18b434273/mza_510582858671591461.jpg/100x100bb.jpg", "collectionPrice": 0.0, "trackPrice": 0.0, "collectionHdPrice": 0, "releaseDate": "2024-01-13T16:47:00Z", "collectionExplicitness": "notExplicit", "trackExplicitness": "cleaned", "trackCount": 222, "trackTimeMillis": 1719, "country": "IDN", "currency": "IDR", "primaryGenreName": "Nature", "contentAdvisoryRating": "Clean", "artworkUrl600": "https://is1-ssl.mzstatic.com/image/thumb/Podcasts114/v4/1c/9a/66/1c9a66eb-dd26-d58f-3353-6fb18b434273/mza_510582858671591461.jpg/600x600bb.jpg", "genreIds": ["1537", "26", "1533"], "genres": ["Nature", "Podcasts", "Science"]}, {"wrapperType": "track", "kind": "podcast", "collectionId": 543708822, "trackId": 543708822, "artistName": "Gary Shapiro", "collectionName": "Gary Shapiro’s From the Bookshelf", "trackName": "Gary Shapiro’s From the Bookshelf", "collectionCensoredName": "Gary Shapiro’s From the Bookshelf", "trackCensoredName": "Gary Shapiro’s From the Bookshelf", "collectionViewUrl": "https://podcasts.apple.com/id/podcast/gary-shapiros-from-the-bookshelf/id543708822?uo=4", "feedUrl": "http://fromthebookshelf.com/feed/podcast/gary-shapiros-from-the-bookshelf/", "trackViewUrl": "https://podcasts.apple.com/id/podcast/gary-shapiros-from-the-bookshelf/id543708822?uo=4", "artworkUrl30": "https://is1-ssl.mzstatic.com/image/thumb/Podcasts211/v4/25/9d/42/259d4203-8a95-8e61-ff3a-18aef1d89b4b/mza_6494420981942859968.jpg/30x30bb.jpg", "artworkUrl60": "https://is1-ssl.mzstatic.com/image/thumb/Podcasts211/v4/25/9d/42/259d4203-8a95-8e61-ff3a-18aef1d89b4b/mza_6494420981942859968.jpg/60x60bb.jpg", "artworkUrl100": "https://is1-ssl.mzstatic.com/image/thumb/Podcasts211/v4/25/9d/42/259d4203-8a95-8e61-ff3a-18aef1d89b4b/mza_6494420981942859968.jpg/100x100bb.jpg", "collectionPrice": 0.0, "trackPrice": 0.0, "collectionHdPrice": 0, "releaseDate": "2026-07-01T18:00:00Z", "collectionExplicitness": "notExplicit", "trackExplicitness": "cleaned", "trackCount": 10, "trackTimeMillis": 3396, "country": "IDN", "currency": "IDR", "primaryGenreName": "Books", "contentAdvisoryRating": "Clean", "artworkUrl600": "https://is1-ssl.mzstatic.com/image/thumb/Podcasts211/v4/25/9d/42/259d4203-8a95-8e61-ff3a-18aef1d89b4b/mza_6494420981942859968.jpg/600x600bb.jpg", "genreIds": ["1482", "26", "1301", "1310"], "genres": ["Books", "Podcasts", "Arts", "Music"]}, {"wrapperType": "track", "kind": "podcast", "collectionId": 1870405017, "trackId": 1870405017, "artistName": "Heartland Church", "collectionName": "Heartland Church Weekly Message", "trackName": "Heartland Church Weekly Message", "collectionCensoredName": "Heartland Church Weekly Message", "trackCensoredName": "Heartland Church Weekly Message", "collectionViewUrl": "https://podcasts.apple.com/id/podcast/heartland-church-weekly-message/id1870405017?uo=4", "feedUrl": "https://anchor.fm/s/10e0c94a0/podcast/rss", "trackViewUrl": "https://podcasts.apple.com/id/podcast/heartland-church-weekly-message/id1870405017?uo=4", "artworkUrl30": "https://is1-ssl.mzstatic.com/image/thumb/Podcasts211/v4/c3/d5/69/c3d5699c-7f5a-ab15-f651-189e7980b2b0/mza_5626665988167594976.jpg/30x30bb.jpg", "artworkUrl60": "https://is1-ssl.mzstatic.com/image/thumb/Podcasts211/v4/c3/d5/69/c3d5699c-7f5a-ab15-f651-189e7980b2b0/mza_5626665988167594976.jpg/60x60bb.jpg", "artworkUrl100": "https://is1-ssl.mzstatic.com/image/thumb/Podcasts211/v4/c3/d5/69/c3d5699c-7f5a-ab15-f651-189e7980b2b0/mza_5626665988167594976.jpg/100x100bb.jpg", "collectionPrice": 0.0, "trackPrice": 0.0, "collectionHdPrice": 0, "releaseDate": "2026-03-15T18:30:00Z", "collectionExplicitness": "notExplicit", "trackExplicitness": "cleaned", "trackCount": 309, "trackTimeMillis": 2627, "country": "IDN", "currency": "IDR", "primaryGenreName": "Christianity", "contentAdvisoryRating": "Clean", "artworkUrl600": "https://is1-ssl.mzstatic.com/image/thumb/Podcasts211/v4/c3/d5/69/c3d5699c-7f5a-ab15-f651-189e7980b2b0/mza_5626665988167594976.jpg/600x600bb.jpg", "genreIds": ["1439", "26", "1314"], "genres": ["Christianity", "Podcasts", "Religion & Spirituality"]}, {"wrapperType": "track", "kind": "podcast", "collectionId": 325810683, "trackId": 325810683, "artistName": "Science Oxford", "collectionName": "Science Oxford Podcasts", "trackName": "Science Oxford Podcasts", "collectionCensoredName": "Science Oxford Podcasts", "trackCensoredName": "Science Oxford Podcasts", "collectionViewUrl": "https://podcasts.apple.com/id/podcast/science-oxford-podcasts/id325810683?uo=4", "feedUrl": "https://feeds.feedburner.com/ScienceOxfordPodcasts", "trackViewUrl": "https://podcasts.apple.com/id/podcast/science-oxford-podcasts/id325810683?uo=4", "artworkUrl30": "https://is1-ssl.mzstatic.com/image/thumb/Features/v4/5f/88/96/5f8896e9-9be5-529a-af14-cc807367568a/mza_1382744875394257421.png/30x30bb.jpg", "artworkUrl60": "https://is1-ssl.mzstatic.com/image/thumb/Features/v4/5f/88/96/5f8896e9-9be5-529a-af14-cc807367568a/mza_1382744875394257421.png/60x60bb.jpg", "artworkUrl100": "https://is1-ssl.mzstatic.com/image/thumb/Features/v4/5f/88/96/5f8896e9-9be5-529a-af14-cc807367568a/mza_1382744875394257421.png/100x100bb.jpg", "collectionPrice": 0.0, "trackPrice": 0.0, "collectionHdPrice": 0, "releaseDate": "2011-09-01T13:55:00Z", "collectionExplicitness": "notExplicit", "trackExplicitness": "cleaned", "trackCount": 25, "country": "IDN", "currency": "IDR", "primaryGenreName": "Science", "contentAdvisoryRating": "Clean", "artworkUrl600": "https://is1-ssl.mzstatic.com/image/thumb/Features/v4/5f/88/96/5f8896e9-9be5-529a-af14-cc807367568a/mza_1382744875394257421.png/600x600bb.jpg", "genreIds": ["1533", "26"], "genres": ["Science", "Podcasts"]}, {"wrapperType": "track", "kind": "podcast", "collectionId": 1465541266, "trackId": 1465541266, "artistName": "Now You Know", "collectionName": "NYK Experts Uncut", "trackName": "NYK Experts Uncut", "collectionCensoredName": "NYK Experts Uncut", "trackCensoredName": "NYK Experts Uncut", "collectionViewUrl": "https://podcasts.apple.com/id/podcast/nyk-experts-uncut/id1465541266?uo=4", "feedUrl": "https://nowyouknow.ca/feed/podcast/nyk-experts-uncut", "trackViewUrl": "https://podcasts.apple.com/id/podcast/nyk-experts-uncut/id1465541266?uo=4", "artworkUrl30": "https://is1-ssl.mzstatic.com/image/thumb/Podcasts123/v4/d9/f5/04/d9f50424-637b-2c8f-324f-19d0e09f41db/mza_6280701018496701942.jpg/30x30bb.jpg", "artworkUrl60": "https://is1-ssl.mzstatic.com/image/thumb/Podcasts123/v4/d9/f5/04/d9f50424-637b-2c8f-324f-19d0e09f41db/mza_6280701018496701942.jpg/60x60bb.jpg", "artworkUrl100": "https://is1-ssl.mzstatic.com/image/thumb/Podcasts123/v4/d9/f5/04/d9f50424-637b-2c8f-324f-19d0e09f41db/mza_6280701018496701942.jpg/100x100bb.jpg", "collectionPrice": 0.0, "trackPrice": 0.0, "collectionHdPrice": 0, "releaseDate": "2020-03-04T05:01:00Z", "collectionExplicitness": "notExplicit", "trackExplicitness": "cleaned", "trackCount": 23, "trackTimeMillis": 1455, "country": "IDN", "currency": "IDR", "primaryGenreName": "Pets & Animals", "contentAdvisoryRating": "Clean", "artworkUrl600": "https://is1-ssl.mzstatic.com/image/thumb/Podcasts123/v4/d9/f5/04/d9f50424-637b-2c8f-324f-19d0e09f41db/mza_6280701018496701942.jpg/600x600bb.jpg", "genreIds": ["1522", "26", "1305", "1324", "1543"], "genres": ["Pets & Animals", "Podcasts", "Kids & Family", "Society & Culture", "Documentary"]}, {"wrapperType": "track", "kind": "podcast", "artistId": 272651214, "collectionId": 1449631195, "trackId": 1449631195, "artistName": "The Economist", "collectionName": "The Intelligence from The Economist", "trackName": "The Intelligence from The Economist", "collectionCensoredName": "The Intelligence from The Economist", "trackCensoredName": "The Intelligence from The Economist", "artistViewUrl": "https://podcasts.apple.com/id/artist/the-economist/272651214?uo=4", "collectionViewUrl": "https://podcasts.apple.com/id/podcast/the-intelligence-from-the-economist/id1449631195?uo=4", "feedUrl": "https://access.acast.com/rss/d556eb54-6160-4c85-95f4-47d9f5216c49", "trackViewUrl": "https://podcasts.apple.com/id/podcast/the-intelligence-from-the-economist/id1449631195?uo=4", "artworkUrl30": "https://is1-ssl.mzstatic.com/image/thumb/Podcasts221/v4/13/a6/58/13a65875-b7c7-a663-9b40-0bb42f62bf74/mza_18066604315473996895.jpeg/30x30bb.jpg", "artworkUrl60": "https://is1-ssl.mzstatic.com/image/thumb/Podcasts221/v4/13/a6/58/13a65875-b7c7-a663-9b40-0bb42f62bf74/mza_18066604315473996895.jpeg/60x60bb.jpg", "artworkUrl100": "https://is1-ssl.mzstatic.com/image/thumb/Podcasts221/v4/13/a6/58/13a65875-b7c7-a663-9b40-0bb42f62bf74/mza_18066604315473996895.jpeg/100x100bb.jpg", "collectionPrice": 0.0, "trackPrice": 0.0, "collectionHdPrice": 0, "releaseDate": "2026-07-10T10:14:00Z", "collectionExplicitness": "notExplicit", "trackExplicitness": "cleaned", "trackCount": 2122, "trackTimeMillis": 1505, "country": "IDN", "currency": "IDR", "primaryGenreName": "Daily News", "contentAdvisoryRating": "Clean", "artworkUrl600": "https://is1-ssl.mzstatic.com/image/thumb/Podcasts221/v4/13/a6/58/13a65875-b7c7-a663-9b40-0bb42f62bf74/mza_18066604315473996895.jpeg/600x600bb.jpg", "genreIds": ["1526", "26", "1489"], "genres": ["Daily News", "Podcasts", "News"]}, {"wrapperType": "track", "kind": "podcast", "artistId": 272651214, "collectionId": 151230264, "trackId": 151230264, "artistName": "The Economist", "collectionName": "Economist Podcasts", "trackName": "Economist Podcasts", "collectionCensoredName": "Economist Podcasts", "trackCensoredName": "Economist Podcasts", "artistViewUrl": "https://podcasts.apple.com/id/artist/the-economist/272651214?uo=4", "collectionViewUrl": "https://podcasts.apple.com/id/podcast/economist-podcasts/id151230264?uo=4", "feedUrl": "https://access.acast.com/rss/ec380acc-fe13-46a0-991f-a1e508d126f8", "trackViewUrl": "https://podcasts.apple.com/id/podcast/economist-podcasts/id151230264?uo=4", "artworkUrl30": "https://is1-ssl.mzstatic.com/image/thumb/Podcasts211/v4/92/68/ba/9268bae8-1bd5-2a15-7f1b-7e265d4773bd/mza_10204374987848109193.png/30x30bb.jpg", "artworkUrl60": "https://is1-ssl.mzstatic.com/image/thumb/Podcasts211/v4/92/68/ba/9268bae8-1bd5-2a15-7f1b-7e265d4773bd/mza_10204374987848109193.png/60x60bb.jpg", "artworkUrl100": "https://is1-ssl.mzstatic.com/image/thumb/Podcasts211/v4/92/68/ba/9268bae8-1bd5-2a15-7f1b-7e265d4773bd/mza_10204374987848109193.png/100x100bb.jpg", "collectionPrice": 0.0, "trackPrice": 0.0, "collectionHdPrice": 0, "releaseDate": "2026-07-11T04:00:00Z", "collectionExplicitness": "notExplicit", "trackExplicitness": "cleaned", "trackCount": 2904, "country": "IDN", "currency": "IDR", "primaryGenreName": "News", "contentAdvisoryRating": "Clean", "artworkUrl600": "https://is1-ssl.mzstatic.com/image/thumb/Podcasts211/v4/92/68/ba/9268bae8-1bd5-2a15-7f1b-7e265d4773bd/mza_10204374987848109193.png/600x600bb.jpg", "genreIds": ["1489", "26"], "genres": ["News", "Podcasts"]}, {"wrapperType": "track", "kind": "podcast", "collectionId": 1514290750, "trackId": 1514290750, "artistName": "Sydney Southeast Asia Centre", "collectionName": "SSEAC Stories", "trackName": "SSEAC Stories", "collectionCensoredName": "SSEAC Stories", "trackCensoredName": "SSEAC Stories", "collectionViewUrl": "https://podcasts.apple.com/id/podcast/sseac-stories/id1514290750?uo=4", "feedUrl": "https://feeds.megaphone.fm/LIT9184634013", "trackViewUrl": "https://podcasts.apple.com/id/podcast/sseac-stories/id1514290750?uo=4", "artworkUrl30": "https://is1-ssl.mzstatic.com/image/thumb/Podcasts221/v4/9a/a7/07/9aa707a4-0387-bad7-ae5a-deba17cc067d/mza_11928898416459480653.jpg/30x30bb.jpg", "artworkUrl60": "https://is1-ssl.mzstatic.com/image/thumb/Podcasts221/v4/9a/a7/07/9aa707a4-0387-bad7-ae5a-deba17cc067d/mza_11928898416459480653.jpg/60x60bb.jpg", "artworkUrl100": "https://is1-ssl.mzstatic.com/image/thumb/Podcasts221/v4/9a/a7/07/9aa707a4-0387-bad7-ae5a-deba17cc067d/mza_11928898416459480653.jpg/100x100bb.jpg", "collectionPrice": 0.0, "trackPrice": 0.0, "collectionHdPrice": 0, "releaseDate": "2025-07-25T08:00:00Z", "collectionExplicitness": "notExplicit", "trackExplicitness": "cleaned", "trackCount": 157, "trackTimeMillis": 1807, "country": "IDN", "currency": "IDR", "primaryGenreName": "News", "contentAdvisoryRating": "Clean", "artworkUrl600": "https://is1-ssl.mzstatic.com/image/thumb/Podcasts221/v4/9a/a7/07/9aa707a4-0387-bad7-ae5a-deba17cc067d/mza_11928898416459480653.jpg/600x600bb.jpg", "genreIds": ["1489", "26"], "genres": ["News", "Podcasts"]}, {"wrapperType": "track", "kind": "podcast", "collectionId": 1542219832, "trackId": 1542219832, "artistName": "Rossika Anjeli", "collectionName": "Rossika Anjeli", "trackName": "Rossika Anjeli", "collectionCensoredName": "Rossika Anjeli", "trackCensoredName": "Rossika Anjeli", "collectionViewUrl": "https://podcasts.apple.com/id/podcast/rossika-anjeli/id1542219832?uo=4", "feedUrl": "https://anchor.fm/s/4126b024/podcast/rss", "trackViewUrl": "https://podcasts.apple.com/id/podcast/rossika-anjeli/id1542219832?uo=4", "artworkUrl30": "https://is1-ssl.mzstatic.com/image/thumb/Podcasts114/v4/40/f2/09/40f209fe-790b-b9b0-7d51-a2d3bd942e1c/mza_11489730009733940777.jpg/30x30bb.jpg", "artworkUrl60": "https://is1-ssl.mzstatic.com/image/thumb/Podcasts114/v4/40/f2/09/40f209fe-790b-b9b0-7d51-a2d3bd942e1c/mza_11489730009733940777.jpg/60x60bb.jpg", "artworkUrl100": "https://is1-ssl.mzstatic.com/image/thumb/Podcasts114/v4/40/f2/09/40f209fe-790b-b9b0-7d51-a2d3bd942e1c/mza_11489730009733940777.jpg/100x100bb.jpg", "collectionPrice": 0.0, "trackPrice": 0.0, "collectionHdPrice": 0, "releaseDate": "2020-11-26T05:51:00Z", "collectionExplicitness": "notExplicit", "trackExplicitness": "cleaned", "trackCount": 1, "trackTimeMillis": 199, "country": "IDN", "currency": "IDR", "primaryGenreName": "Education", "contentAdvisoryRating": "Clean", "artworkUrl600": "https://is1-ssl.mzstatic.com/image/thumb/Podcasts114/v4/40/f2/09/40f209fe-790b-b9b0-7d51-a2d3bd942e1c/mza_11489730009733940777.jpg/600x600bb.jpg", "genreIds": ["1304", "26"], "genres": ["Education", "Podcasts"]}, {"wrapperType": "track", "kind": "podcast", "artistId": 1510597239, "collectionId": 425223410, "trackId": 425223410, "artistName": "Marshall Poe", "collectionName": "New Books in Environmental Studies", "trackName": "New Books in Environmental Studies", "collectionCensoredName": "New Books in Environmental Studies", "trackCensoredName": "New Books in Environmental Studies", "artistViewUrl": "https://podcasts.apple.com/id/artist/new-books-network/1510597239?uo=4", "collectionViewUrl": "https://podcasts.apple.com/id/podcast/new-books-in-environmental-studies/id425223410?uo=4", "feedUrl": "https://feeds.megaphone.fm/LIT4982261480", "trackViewUrl": "https://podcasts.apple.com/id/podcast/new-books-in-environmental-studies/id425223410?uo=4", "artworkUrl30": "https://is1-ssl.mzstatic.com/image/thumb/Podcasts116/v4/98/fc/f1/98fcf172-dc93-1e42-1b25-16a278ceb5df/mza_16526382866342398132.jpeg/30x30bb.jpg", "artworkUrl60": "https://is1-ssl.mzstatic.com/image/thumb/Podcasts116/v4/98/fc/f1/98fcf172-dc93-1e42-1b25-16a278ceb5df/mza_16526382866342398132.jpeg/60x60bb.jpg", "artworkUrl100": "https://is1-ssl.mzstatic.com/image/thumb/Podcasts116/v4/98/fc/f1/98fcf172-dc93-1e42-1b25-16a278ceb5df/mza_16526382866342398132.jpeg/100x100bb.jpg", "collectionPrice": 0.0, "trackPrice": 0.0, "collectionHdPrice": 0, "releaseDate": "2026-07-10T08:00:00Z", "collectionExplicitness": "notExplicit", "trackExplicitness": "cleaned", "trackCount": 1255, "trackTimeMillis": 2597, "country": "IDN", "currency": "IDR", "primaryGenreName": "Natural Sciences", "contentAdvisoryRating": "Clean", "artworkUrl600": "https://is1-ssl.mzstatic.com/image/thumb/Podcasts116/v4/98/fc/f1/98fcf172-dc93-1e42-1b25-16a278ceb5df/mza_16526382866342398132.jpeg/600x600bb.jpg", "genreIds": ["1534", "26", "1533"], "genres": ["Natural Sciences", "Podcasts", "Science"]}, {"wrapperType": "track", "kind": "podcast", "collectionId": 1514976777, "trackId": 1514976777, "artistName": "IHRB, Institute for Human Rights and Business", "collectionName": "Voices - Conversations on Business and Human Rights from Around the World", "trackName": "Voices - Conversations on Business and Human Rights from Around the World", "collectionCensoredName": "Voices - Conversations on Business and Human Rights from Around the World", "trackCensoredName": "Voices - Conversations on Business and Human Rights from Around the World", "collectionViewUrl": "https://podcasts.apple.com/id/podcast/voices-conversations-on-business-and-human-rights/id1514976777?uo=4", "feedUrl": "https://feeds.simplecast.com/RJx8IHPu", "trackViewUrl": "https://podcasts.apple.com/id/podcast/voices-conversations-on-business-and-human-rights/id1514976777?uo=4", "artworkUrl30": "https://is1-ssl.mzstatic.com/image/thumb/Podcasts221/v4/64/58/89/6458892c-f912-096c-bf0e-591501c8d5ea/mza_9964690376101396891.jpg/30x30bb.jpg", "artworkUrl60": "https://is1-ssl.mzstatic.com/image/thumb/Podcasts221/v4/64/58/89/6458892c-f912-096c-bf0e-591501c8d5ea/mza_9964690376101396891.jpg/60x60bb.jpg", "artworkUrl100": "https://is1-ssl.mzstatic.com/image/thumb/Podcasts221/v4/64/58/89/6458892c-f912-096c-bf0e-591501c8d5ea/mza_9964690376101396891.jpg/100x100bb.jpg", "collectionPrice": 0.0, "trackPrice": 0.0, "collectionHdPrice": 0, "releaseDate": "2026-06-15T11:45:00Z", "collectionExplicitness": "notExplicit", "trackExplicitness": "cleaned", "trackCount": 176, "trackTimeMillis": 1823, "country": "IDN", "currency": "IDR", "primaryGenreName": "Society & Culture", "contentAdvisoryRating": "Clean", "artworkUrl600": "https://is1-ssl.mzstatic.com/image/thumb/Podcasts221/v4/64/58/89/6458892c-f912-096c-bf0e-591501c8d5ea/mza_9964690376101396891.jpg/600x600bb.jpg", "genreIds": ["1324", "26", "1321"], "genres": ["Society & Culture", "Podcasts", "Business"]}, {"wrapperType": "track", "kind": "podcast", "artistId": 1510597239, "collectionId": 425214664, "trackId": 425214664, "artistName": "New Books Network", "collectionName": "New Books in Southeast Asian Studies", "trackName": "New Books in Southeast Asian Studies", "collectionCensoredName": "New Books in Southeast Asian Studies", "trackCensoredName": "New Books in Southeast Asian Studies", "artistViewUrl": "https://podcasts.apple.com/id/artist/new-books-network/1510597239?uo=4", "collectionViewUrl": "https://podcasts.apple.com/id/podcast/new-books-in-southeast-asian-studies/id425214664?uo=4", "feedUrl": "https://feeds.megaphone.fm/LIT4430509368", "trackViewUrl": "https://podcasts.apple.com/id/podcast/new-books-in-southeast-asian-studies/id425214664?uo=4", "artworkUrl30": "https://is1-ssl.mzstatic.com/image/thumb/Podcasts122/v4/43/6b/2b/436b2b1c-781a-b445-c413-13be3ba7e9fc/mza_6387629479463740695.jpeg/30x30bb.jpg", "artworkUrl60": "https://is1-ssl.mzstatic.com/image/thumb/Podcasts122/v4/43/6b/2b/436b2b1c-781a-b445-c413-13be3ba7e9fc/mza_6387629479463740695.jpeg/60x60bb.jpg", "artworkUrl100": "https://is1-ssl.mzstatic.com/image/thumb/Podcasts122/v4/43/6b/2b/436b2b1c-781a-b445-c413-13be3ba7e9fc/mza_6387629479463740695.jpeg/100x100bb.jpg", "collectionPrice": 0.0, "trackPrice": 0.0, "collectionHdPrice": 0, "releaseDate": "2026-06-24T08:00:00Z", "collectionExplicitness": "notExplicit", "trackExplicitness": "cleaned", "trackCount": 703, "trackTimeMillis": 2560, "country": "IDN", "currency": "IDR", "primaryGenreName": "Society & Culture", "contentAdvisoryRating": "Clean", "artworkUrl600": "https://is1-ssl.mzstatic.com/image/thumb/Podcasts122/v4/43/6b/2b/436b2b1c-781a-b445-c413-13be3ba7e9fc/mza_6387629479463740695.jpeg/600x600bb.jpg", "genreIds": ["1324", "26", "1487"], "genres": ["Society & Culture", "Podcasts", "History"]}, {"wrapperType": "track", "kind": "podcast", "collectionId": 1606989678, "trackId": 1606989678, "artistName": "Michelle Cheripka, Open Environmental Data Project, Madhuri Karak", "collectionName": "Data Dialogues", "trackName": "Data Dialogues", "collectionCensoredName": "Data Dialogues", "trackCensoredName": "Data Dialogues", "collectionViewUrl": "https://podcasts.apple.com/id/podcast/data-dialogues/id1606989678?uo=4", "feedUrl": "https://feeds.simplecast.com/zUGwCMXU", "trackViewUrl": "https://podcasts.apple.com/id/podcast/data-dialogues/id1606989678?uo=4", "artworkUrl30": "https://is1-ssl.mzstatic.com/image/thumb/Podcasts211/v4/0d/e2/25/0de22554-e60f-bf07-0114-2c793a0f0456/mza_6875669509626286662.jpg/30x30bb.jpg", "artworkUrl60": "https://is1-ssl.mzstatic.com/image/thumb/Podcasts211/v4/0d/e2/25/0de22554-e60f-bf07-0114-2c793a0f0456/mza_6875669509626286662.jpg/60x60bb.jpg", "artworkUrl100": "https://is1-ssl.mzstatic.com/image/thumb/Podcasts211/v4/0d/e2/25/0de22554-e60f-bf07-0114-2c793a0f0456/mza_6875669509626286662.jpg/100x100bb.jpg", "collectionPrice": 0.0, "trackPrice": 0.0, "collectionHdPrice": 0, "releaseDate": "2024-09-11T06:00:00Z", "collectionExplicitness": "notExplicit", "trackExplicitness": "cleaned", "trackCount": 35, "trackTimeMillis": 1005, "country": "IDN", "currency": "IDR", "primaryGenreName": "Government", "contentAdvisoryRating": "Clean", "artworkUrl600": "https://is1-ssl.mzstatic.com/image/thumb/Podcasts211/v4/0d/e2/25/0de22554-e60f-bf07-0114-2c793a0f0456/mza_6875669509626286662.jpg/600x600bb.jpg", "genreIds": ["1511", "26", "1487"], "genres": ["Government", "Podcasts", "History"]}, {"wrapperType": "track", "kind": "podcast", "collectionId": 1106739747, "trackId": 1106739747, "artistName": "Steve Zwick", "collectionName": "Bionic Planet: Reversing Climate Change by Restoring Nature", "trackName": "Bionic Planet: Reversing Climate Change by Restoring Nature", "collectionCensoredName": "Bionic Planet: Reversing Climate Change by Restoring Nature", "trackCensoredName": "Bionic Planet: Reversing Climate Change by Restoring Nature", "collectionViewUrl": "https://podcasts.apple.com/id/podcast/bionic-planet-reversing-climate-change-by-restoring/id1106739747?uo=4", "feedUrl": "https://rss.pdrl.fm/494161/feeds.libsyn.com/81028/rss/?redirect=false", "trackViewUrl": "https://podcasts.apple.com/id/podcast/bionic-planet-reversing-climate-change-by-restoring/id1106739747?uo=4", "artworkUrl30": "https://is1-ssl.mzstatic.com/image/thumb/Podcasts116/v4/80/71/ad/8071ad91-6417-fbef-aaa7-61ae2c7e62a2/mza_8189696580713087530.jpg/30x30bb.jpg", "artworkUrl60": "https://is1-ssl.mzstatic.com/image/thumb/Podcasts116/v4/80/71/ad/8071ad91-6417-fbef-aaa7-61ae2c7e62a2/mza_8189696580713087530.jpg/60x60bb.jpg", "artworkUrl100": "https://is1-ssl.mzstatic.com/image/thumb/Podcasts116/v4/80/71/ad/8071ad91-6417-fbef-aaa7-61ae2c7e62a2/mza_8189696580713087530.jpg/100x100bb.jpg", "collectionPrice": 0.0, "trackPrice": 0.0, "collectionHdPrice": 0, "releaseDate": "2025-10-06T21:38:00Z", "collectionExplicitness": "notExplicit", "trackExplicitness": "cleaned", "trackCount": 95, "trackTimeMillis": 8779, "country": "IDN", "currency": "IDR", "primaryGenreName": "Earth Sciences", "contentAdvisoryRating": "Clean", "artworkUrl600": "https://is1-ssl.mzstatic.com/image/thumb/Podcasts116/v4/80/71/ad/8071ad91-6417-fbef-aaa7-61ae2c7e62a2/mza_8189696580713087530.jpg/600x600bb.jpg", "genreIds": ["1540", "26", "1533"], "genres": ["Earth Sciences", "Podcasts", "Science"]}, {"wrapperType": "track", "kind": "podcast", "collectionId": 1510860088, "trackId": 1510860088, "artistName": "Maria Ugrinovski | Casper Magazine", "collectionName": "Staying Alive and Rich", "trackName": "Staying Alive and Rich", "collectionCensoredName": "Staying Alive and Rich", "trackCensoredName": "Staying Alive and Rich", "collectionViewUrl": "https://podcasts.apple.com/id/podcast/staying-alive-and-rich/id1510860088?uo=4", "feedUrl": "https://anchor.fm/s/eaeb52cc/podcast/rss", "trackViewUrl": "https://podcasts.apple.com/id/podcast/staying-alive-and-rich/id1510860088?uo=4", "artworkUrl30": "https://is1-ssl.mzstatic.com/image/thumb/Podcasts116/v4/67/43/06/67430693-59f9-7f64-0d80-17d8897994d6/mza_17862878571600473126.jpg/30x30bb.jpg", "artworkUrl60": "https://is1-ssl.mzstatic.com/image/thumb/Podcasts116/v4/67/43/06/67430693-59f9-7f64-0d80-17d8897994d6/mza_17862878571600473126.jpg/60x60bb.jpg", "artworkUrl100": "https://is1-ssl.mzstatic.com/image/thumb/Podcasts116/v4/67/43/06/67430693-59f9-7f64-0d80-17d8897994d6/mza_17862878571600473126.jpg/100x100bb.jpg", "collectionPrice": 0.0, "trackPrice": 0.0, "collectionHdPrice": 0, "releaseDate": "2024-06-26T05:42:00Z", "collectionExplicitness": "notExplicit", "trackExplicitness": "cleaned", "trackCount": 47, "trackTimeMillis": 2232, "country": "IDN", "currency": "IDR", "primaryGenreName": "Self-Improvement", "contentAdvisoryRating": "Clean", "artworkUrl600": "https://is1-ssl.mzstatic.com/image/thumb/Podcasts116/v4/67/43/06/67430693-59f9-7f64-0d80-17d8897994d6/mza_17862878571600473126.jpg/600x600bb.jpg", "genreIds": ["1500", "26", "1304"], "genres": ["Self-Improvement", "Podcasts", "Education"]}, {"wrapperType": "track", "kind": "podcast", "collectionId": 1276105469, "trackId": 1276105469, "artistName": "Morning Run", "collectionName": "Current Affairs", "trackName": "Current Affairs", "collectionCensoredName": "Current Affairs", "trackCensoredName": "Current Affairs", "collectionViewUrl": "https://podcasts.apple.com/id/podcast/current-affairs/id1276105469?uo=4", "feedUrl": "https://www.omnycontent.com/d/playlist/de62ff84-6498-49d0-a266-a9d50120c712/f90b19c6-7840-4730-bbb8-ab0900403745/9099b628-967e-4ff0-ab1f-ab090040374f/podcast.rss", "trackViewUrl": "https://podcasts.apple.com/id/podcast/current-affairs/id1276105469?uo=4", "artworkUrl30": "https://is1-ssl.mzstatic.com/image/thumb/Podcasts126/v4/de/a3/be/dea3be66-5ce6-73de-299c-8d8482342a28/mza_5721984568066439239.jpg/30x30bb.jpg", "artworkUrl60": "https://is1-ssl.mzstatic.com/image/thumb/Podcasts126/v4/de/a3/be/dea3be66-5ce6-73de-299c-8d8482342a28/mza_5721984568066439239.jpg/60x60bb.jpg", "artworkUrl100": "https://is1-ssl.mzstatic.com/image/thumb/Podcasts126/v4/de/a3/be/dea3be66-5ce6-73de-299c-8d8482342a28/mza_5721984568066439239.jpg/100x100bb.jpg", "collectionPrice": 0.0, "trackPrice": 0.0, "collectionHdPrice": 0, "releaseDate": "2020-02-25T10:00:00Z", "collectionExplicitness": "notExplicit", "trackExplicitness": "cleaned", "trackCount": 1426, "trackTimeMillis": 599, "country": "IDN", "currency": "IDR", "primaryGenreName": "Entertainment News", "contentAdvisoryRating": "Clean", "artworkUrl600": "https://is1-ssl.mzstatic.com/image/thumb/Podcasts126/v4/de/a3/be/dea3be66-5ce6-73de-299c-8d8482342a28/mza_5721984568066439239.jpg/600x600bb.jpg", "genreIds": ["1531", "26", "1489"], "genres": ["Entertainment News", "Podcasts", "News"]}, {"wrapperType": "track", "kind": "podcast", "collectionId": 1775383477, "trackId": 1775383477, "artistName": "Khanh-Linh", "collectionName": "Forest Builders", "trackName": "Forest Builders", "collectionCensoredName": "Forest Builders", "trackCensoredName": "Forest Builders", "collectionViewUrl": "https://podcasts.apple.com/id/podcast/forest-builders/id1775383477?uo=4", "feedUrl": "https://feeds.acast.com/public/shows/6717621530187dfb6c592c03", "trackViewUrl": "https://podcasts.apple.com/id/podcast/forest-builders/id1775383477?uo=4", "artworkUrl30": "https://is1-ssl.mzstatic.com/image/thumb/Podcasts211/v4/46/d9/41/46d941f5-45e8-2ae8-b339-6e5d84441cf2/mza_16823049485663684183.jpeg/30x30bb.jpg", "artworkUrl60": "https://is1-ssl.mzstatic.com/image/thumb/Podcasts211/v4/46/d9/41/46d941f5-45e8-2ae8-b339-6e5d84441cf2/mza_16823049485663684183.jpeg/60x60bb.jpg", "artworkUrl100": "https://is1-ssl.mzstatic.com/image/thumb/Podcasts211/v4/46/d9/41/46d941f5-45e8-2ae8-b339-6e5d84441cf2/mza_16823049485663684183.jpeg/100x100bb.jpg", "collectionPrice": 0.0, "trackPrice": 0.0, "collectionHdPrice": 0, "releaseDate": "2026-02-12T13:56:00Z", "collectionExplicitness": "notExplicit", "trackExplicitness": "cleaned", "trackCount": 10, "trackTimeMillis": 3701, "country": "IDN", "currency": "IDR", "primaryGenreName": "Nature", "contentAdvisoryRating": "Clean", "artworkUrl600": "https://is1-ssl.mzstatic.com/image/thumb/Podcasts211/v4/46/d9/41/46d941f5-45e8-2ae8-b339-6e5d84441cf2/mza_16823049485663684183.jpeg/600x600bb.jpg", "genreIds": ["1537", "26", "1533", "1321", "1493"], "genres": ["Nature", "Podcasts", "Science", "Business", "Entrepreneurship"]}, {"wrapperType": "track", "kind": "podcast", "collectionId": 1632477554, "trackId": 1632477554, "artistName": "Indian Ocean World Centre", "collectionName": "The Indian Ocean World Podcast", "trackName": "The Indian Ocean World Podcast", "collectionCensoredName": "The Indian Ocean World Podcast", "trackCensoredName": "The Indian Ocean World Podcast", "collectionViewUrl": "https://podcasts.apple.com/id/podcast/the-indian-ocean-world-podcast/id1632477554?uo=4", "feedUrl": "https://feed.podbean.com/iowpodcast/feed.xml", "trackViewUrl": "https://podcasts.apple.com/id/podcast/the-indian-ocean-world-podcast/id1632477554?uo=4", "artworkUrl30": "https://is1-ssl.mzstatic.com/image/thumb/Podcasts126/v4/88/37/a8/8837a809-0d4e-8bb0-a193-1d4f42a53aa0/mza_14953009912399402249.png/30x30bb.jpg", "artworkUrl60": "https://is1-ssl.mzstatic.com/image/thumb/Podcasts126/v4/88/37/a8/8837a809-0d4e-8bb0-a193-1d4f42a53aa0/mza_14953009912399402249.png/60x60bb.jpg", "artworkUrl100": "https://is1-ssl.mzstatic.com/image/thumb/Podcasts126/v4/88/37/a8/8837a809-0d4e-8bb0-a193-1d4f42a53aa0/mza_14953009912399402249.png/100x100bb.jpg", "collectionPrice": 0.0, "trackPrice": 0.0, "collectionHdPrice": 0, "releaseDate": "2026-04-06T15:38:00Z", "collectionExplicitness": "notExplicit", "trackExplicitness": "cleaned", "trackCount": 79, "trackTimeMillis": 3182, "country": "IDN", "currency": "IDR", "primaryGenreName": "History", "contentAdvisoryRating": "Clean", "artworkUrl600": "https://is1-ssl.mzstatic.com/image/thumb/Podcasts126/v4/88/37/a8/8837a809-0d4e-8bb0-a193-1d4f42a53aa0/mza_14953009912399402249.png/600x600bb.jpg", "genreIds": ["1487", "26", "1304"], "genres": ["History", "Podcasts", "Education"]}, {"wrapperType": "track", "kind": "podcast", "artistId": 313208901, "collectionId": 312418293, "trackId": 312418293, "artistName": "Carnegie Council for Ethics in International Affairs", "collectionName": "Carnegie Council Podcasts", "trackName": "Carnegie Council Podcasts", "collectionCensoredName": "Carnegie Council Podcasts", "trackCensoredName": "Carnegie Council Podcasts", "artistViewUrl": "https://podcasts.apple.com/id/artist/carnegie-council/313208901?uo=4", "collectionViewUrl": "https://podcasts.apple.com/id/podcast/carnegie-council-podcasts/id312418293?uo=4", "feedUrl": "https://rss.libsyn.com/shows/148595/destinations/952415.xml", "trackViewUrl": "https://podcasts.apple.com/id/podcast/carnegie-council-podcasts/id312418293?uo=4", "artworkUrl30": "https://is1-ssl.mzstatic.com/image/thumb/Podcasts221/v4/5a/ec/73/5aec73a6-24eb-e40c-a7c3-c168df25bdf1/mza_3708297267775235015.jpg/30x30bb.jpg", "artworkUrl60": "https://is1-ssl.mzstatic.com/image/thumb/Podcasts221/v4/5a/ec/73/5aec73a6-24eb-e40c-a7c3-c168df25bdf1/mza_3708297267775235015.jpg/60x60bb.jpg", "artworkUrl100": "https://is1-ssl.mzstatic.com/image/thumb/Podcasts221/v4/5a/ec/73/5aec73a6-24eb-e40c-a7c3-c168df25bdf1/mza_3708297267775235015.jpg/100x100bb.jpg", "collectionPrice": 0.0, "trackPrice": 0.0, "collectionHdPrice": 0, "releaseDate": "2026-06-29T16:42:00Z", "collectionExplicitness": "notExplicit", "trackExplicitness": "cleaned", "trackCount": 754, "trackTimeMillis": 3547, "country": "IDN", "currency": "IDR", "primaryGenreName": "News Commentary", "contentAdvisoryRating": "Clean", "artworkUrl600": "https://is1-ssl.mzstatic.com/image/thumb/Podcasts221/v4/5a/ec/73/5aec73a6-24eb-e40c-a7c3-c168df25bdf1/mza_3708297267775235015.jpg/600x600bb.jpg", "genreIds": ["1530", "26", "1489", "1321", "1494"], "genres": ["News Commentary", "Podcasts", "News", "Business", "Non-Profit"]}, {"wrapperType": "track", "kind": "podcast", "artistId": 313208901, "collectionId": 130062462, "trackId": 130062462, "artistName": "Carnegie Council for Ethics in International Affairs", "collectionName": "Carnegie Council Podcasts", "trackName": "Carnegie Council Podcasts", "collectionCensoredName": "Carnegie Council Podcasts", "trackCensoredName": "Carnegie Council Podcasts", "artistViewUrl": "https://podcasts.apple.com/id/artist/carnegie-council/313208901?uo=4", "collectionViewUrl": "https://podcasts.apple.com/id/podcast/carnegie-council-podcasts/id130062462?uo=4", "feedUrl": "https://rss.libsyn.com/shows/148595/destinations/952415.xml", "trackViewUrl": "https://podcasts.apple.com/id/podcast/carnegie-council-podcasts/id130062462?uo=4", "artworkUrl30": "https://is1-ssl.mzstatic.com/image/thumb/Podcasts211/v4/d9/37/d7/d937d798-a1a6-52b5-0079-f4c5a46d00de/mza_11817901109347181541.jpg/30x30bb.jpg", "artworkUrl60": "https://is1-ssl.mzstatic.com/image/thumb/Podcasts211/v4/d9/37/d7/d937d798-a1a6-52b5-0079-f4c5a46d00de/mza_11817901109347181541.jpg/60x60bb.jpg", "artworkUrl100": "https://is1-ssl.mzstatic.com/image/thumb/Podcasts211/v4/d9/37/d7/d937d798-a1a6-52b5-0079-f4c5a46d00de/mza_11817901109347181541.jpg/100x100bb.jpg", "collectionPrice": 0.0, "trackPrice": 0.0, "collectionHdPrice": 0, "releaseDate": "2026-06-29T16:42:00Z", "collectionExplicitness": "notExplicit", "trackExplicitness": "cleaned", "trackCount": 754, "trackTimeMillis": 3547, "country": "IDN", "currency": "IDR", "primaryGenreName": "News Commentary", "contentAdvisoryRating": "Clean", "artworkUrl600": "https://is1-ssl.mzstatic.com/image/thumb/Podcasts211/v4/d9/37/d7/d937d798-a1a6-52b5-0079-f4c5a46d00de/mza_11817901109347181541.jpg/600x600bb.jpg", "genreIds": ["1530", "26", "1489", "1321", "1494"], "genres": ["News Commentary", "Podcasts", "News", "Business", "Non-Profit"]}, {"wrapperType": "track", "kind": "podcast", "collectionId": 1499927535, "trackId": 1499927535, "artistName": "Ubud Writers & Readers Festival", "collectionName": "Ubud Writers & Readers Festival Podcast", "trackName": "Ubud Writers & Readers Festival Podcast", "collectionCensoredName": "Ubud Writers & Readers Festival Podcast", "trackCensoredName": "Ubud Writers & Readers Festival Podcast", "collectionViewUrl": "https://podcasts.apple.com/id/podcast/ubud-writers-readers-festival-podcast/id1499927535?uo=4", "feedUrl": "https://feeds.simplecast.com/eUhy4nqz", "trackViewUrl": "https://podcasts.apple.com/id/podcast/ubud-writers-readers-festival-podcast/id1499927535?uo=4", "artworkUrl30": "https://is1-ssl.mzstatic.com/image/thumb/Podcasts126/v4/aa/81/ac/aa81ac1c-b162-e326-250a-b793777b68d0/mza_12033997694951667945.jpg/30x30bb.jpg", "artworkUrl60": "https://is1-ssl.mzstatic.com/image/thumb/Podcasts126/v4/aa/81/ac/aa81ac1c-b162-e326-250a-b793777b68d0/mza_12033997694951667945.jpg/60x60bb.jpg", "artworkUrl100": "https://is1-ssl.mzstatic.com/image/thumb/Podcasts126/v4/aa/81/ac/aa81ac1c-b162-e326-250a-b793777b68d0/mza_12033997694951667945.jpg/100x100bb.jpg", "collectionPrice": 0.0, "trackPrice": 0.0, "collectionHdPrice": 0, "releaseDate": "2026-03-16T01:00:00Z", "collectionExplicitness": "notExplicit", "trackExplicitness": "cleaned", "trackCount": 149, "trackTimeMillis": 3672, "country": "IDN", "currency": "IDR", "primaryGenreName": "Books", "contentAdvisoryRating": "Clean", "artworkUrl600": "https://is1-ssl.mzstatic.com/image/thumb/Podcasts126/v4/aa/81/ac/aa81ac1c-b162-e326-250a-b793777b68d0/mza_12033997694951667945.jpg/600x600bb.jpg", "genreIds": ["1482", "26", "1301", "1304", "1499"], "genres": ["Books", "Podcasts", "Arts", "Education", "How To"]}, {"wrapperType": "track", "kind": "podcast", "collectionId": 1522931430, "trackId": 1522931430, "artistName": "Honey Roasted T-Shirts", "collectionName": "The Jay Luck Club", "trackName": "The Jay Luck Club", "collectionCensoredName": "The Jay Luck Club", "trackCensoredName": "The Jay Luck Club", "collectionViewUrl": "https://podcasts.apple.com/id/podcast/the-jay-luck-club/id1522931430?uo=4", "feedUrl": "https://feed.podbean.com/www.thejayluckclubpodcast.com/feed.xml", "trackViewUrl": "https://podcasts.apple.com/id/podcast/the-jay-luck-club/id1522931430?uo=4", "artworkUrl30": "https://is1-ssl.mzstatic.com/image/thumb/Podcasts115/v4/9a/c9/02/9ac90281-00a1-5c24-64b5-09f356c8f831/mza_12604395691677165759.jpg/30x30bb.jpg", "artworkUrl60": "https://is1-ssl.mzstatic.com/image/thumb/Podcasts115/v4/9a/c9/02/9ac90281-00a1-5c24-64b5-09f356c8f831/mza_12604395691677165759.jpg/60x60bb.jpg", "artworkUrl100": "https://is1-ssl.mzstatic.com/image/thumb/Podcasts115/v4/9a/c9/02/9ac90281-00a1-5c24-64b5-09f356c8f831/mza_12604395691677165759.jpg/100x100bb.jpg", "collectionPrice": 0.0, "trackPrice": 0.0, "collectionHdPrice": 0, "releaseDate": "2021-06-03T09:02:00Z", "collectionExplicitness": "notExplicit", "trackExplicitness": "cleaned", "trackCount": 19, "trackTimeMillis": 2446, "country": "IDN", "currency": "IDR", "primaryGenreName": "Places & Travel", "contentAdvisoryRating": "Clean", "artworkUrl600": "https://is1-ssl.mzstatic.com/image/thumb/Podcasts115/v4/9a/c9/02/9ac90281-00a1-5c24-64b5-09f356c8f831/mza_12604395691677165759.jpg/600x600bb.jpg", "genreIds": ["1320", "26", "1324", "1302"], "genres": ["Places & Travel", "Podcasts", "Society & Culture", "Personal Journals"]}, {"wrapperType": "track", "kind": "podcast", "collectionId": 1514894492, "trackId": 1514894492, "artistName": "nomadcoops820", "collectionName": "Itchy Feet: Travel Tips and Stories from Backpackers Worldwide", "trackName": "Itchy Feet: Travel Tips and Stories from Backpackers Worldwide", "collectionCensoredName": "Itchy Feet: Travel Tips and Stories from Backpackers Worldwide", "trackCensoredName": "Itchy Feet: Travel Tips and Stories from Backpackers Worldwide", "collectionViewUrl": "https://podcasts.apple.com/id/podcast/itchy-feet-travel-tips-and-stories-from-backpackers/id1514894492?uo=4", "feedUrl": "https://anchor.fm/s/22db10b0/podcast/rss", "trackViewUrl": "https://podcasts.apple.com/id/podcast/itchy-feet-travel-tips-and-stories-from-backpackers/id1514894492?uo=4", "artworkUrl30": "https://is1-ssl.mzstatic.com/image/thumb/Podcasts125/v4/b3/b6/d5/b3b6d569-12f6-925f-ad33-16be6ed9a249/mza_13668616758578727568.jpeg/30x30bb.jpg", "artworkUrl60": "https://is1-ssl.mzstatic.com/image/thumb/Podcasts125/v4/b3/b6/d5/b3b6d569-12f6-925f-ad33-16be6ed9a249/mza_13668616758578727568.jpeg/60x60bb.jpg", "artworkUrl100": "https://is1-ssl.mzstatic.com/image/thumb/Podcasts125/v4/b3/b6/d5/b3b6d569-12f6-925f-ad33-16be6ed9a249/mza_13668616758578727568.jpeg/100x100bb.jpg", "collectionPrice": 0.0, "trackPrice": 0.0, "collectionHdPrice": 0, "releaseDate": "2021-01-13T01:51:00Z", "collectionExplicitness": "notExplicit", "trackExplicitness": "cleaned", "trackCount": 17, "trackTimeMillis": 1898, "country": "IDN", "currency": "IDR", "primaryGenreName": "Places & Travel", "contentAdvisoryRating": "Clean", "artworkUrl600": "https://is1-ssl.mzstatic.com/image/thumb/Podcasts125/v4/b3/b6/d5/b3b6d569-12f6-925f-ad33-16be6ed9a249/mza_13668616758578727568.jpeg/600x600bb.jpg", "genreIds": ["1320", "26", "1324"], "genres": ["Places & Travel", "Podcasts", "Society & Culture"]}, {"wrapperType": "track", "kind": "podcast", "collectionId": 1737448295, "trackId": 1737448295, "artistName": "One Nine Nine", "collectionName": "The Sustainable Commodities Podcast", "trackName": "The Sustainable Commodities Podcast", "collectionCensoredName": "The Sustainable Commodities Podcast", "trackCensoredName": "The Sustainable Commodities Podcast", "collectionViewUrl": "https://podcasts.apple.com/id/podcast/the-sustainable-commodities-podcast/id1737448295?uo=4", "feedUrl": "https://feeds.fireside.fm/thesustainablecommoditiespodcast/rss", "trackViewUrl": "https://podcasts.apple.com/id/podcast/the-sustainable-commodities-podcast/id1737448295?uo=4", "artworkUrl30": "https://is1-ssl.mzstatic.com/image/thumb/Podcasts211/v4/4c/85/a9/4c85a9c7-202d-6028-728b-e77ebab8b53e/mza_7499373152358741772.jpg/30x30bb.jpg", "artworkUrl60": "https://is1-ssl.mzstatic.com/image/thumb/Podcasts211/v4/4c/85/a9/4c85a9c7-202d-6028-728b-e77ebab8b53e/mza_7499373152358741772.jpg/60x60bb.jpg", "artworkUrl100": "https://is1-ssl.mzstatic.com/image/thumb/Podcasts211/v4/4c/85/a9/4c85a9c7-202d-6028-728b-e77ebab8b53e/mza_7499373152358741772.jpg/100x100bb.jpg", "collectionPrice": 0.0, "trackPrice": 0.0, "collectionHdPrice": 0, "releaseDate": "2026-06-22T08:00:00Z", "collectionExplicitness": "notExplicit", "trackExplicitness": "cleaned", "trackCount": 39, "trackTimeMillis": 2762, "country": "IDN", "currency": "IDR", "primaryGenreName": "Business", "contentAdvisoryRating": "Clean", "artworkUrl600": "https://is1-ssl.mzstatic.com/image/thumb/Podcasts211/v4/4c/85/a9/4c85a9c7-202d-6028-728b-e77ebab8b53e/mza_7499373152358741772.jpg/600x600bb.jpg", "genreIds": ["1321", "26", "1533", "1540"], "genres": ["Business", "Podcasts", "Science", "Earth Sciences"]}, {"wrapperType": "track", "kind": "podcast", "collectionId": 1572266981, "trackId": 1572266981, "artistName": "BOS Foundation", "collectionName": "OuCast by BOS Foundation", "trackName": "OuCast by BOS Foundation", "collectionCensoredName": "OuCast by BOS Foundation", "trackCensoredName": "OuCast by BOS Foundation", "collectionViewUrl": "https://podcasts.apple.com/id/podcast/oucast-by-bos-foundation/id1572266981?uo=4", "feedUrl": "https://anchor.fm/s/5d75e358/podcast/rss", "trackViewUrl": "https://podcasts.apple.com/id/podcast/oucast-by-bos-foundation/id1572266981?uo=4", "artworkUrl30": "https://is1-ssl.mzstatic.com/image/thumb/Podcasts211/v4/da/91/3e/da913ea0-7322-427b-345a-220240131996/mza_18166502528347123139.jpg/30x30bb.jpg", "artworkUrl60": "https://is1-ssl.mzstatic.com/image/thumb/Podcasts211/v4/da/91/3e/da913ea0-7322-427b-345a-220240131996/mza_18166502528347123139.jpg/60x60bb.jpg", "artworkUrl100": "https://is1-ssl.mzstatic.com/image/thumb/Podcasts211/v4/da/91/3e/da913ea0-7322-427b-345a-220240131996/mza_18166502528347123139.jpg/100x100bb.jpg", "collectionPrice": 0.0, "trackPrice": 0.0, "collectionHdPrice": 0, "releaseDate": "2026-01-27T06:06:00Z", "collectionExplicitness": "notExplicit", "trackExplicitness": "cleaned", "trackCount": 12, "trackTimeMillis": 2661, "country": "IDN", "currency": "IDR", "primaryGenreName": "Non-Profit", "contentAdvisoryRating": "Clean", "artworkUrl600": "https://is1-ssl.mzstatic.com/image/thumb/Podcasts211/v4/da/91/3e/da913ea0-7322-427b-345a-220240131996/mza_18166502528347123139.jpg/600x600bb.jpg", "genreIds": ["1494", "26", "1321"], "genres": ["Non-Profit", "Podcasts", "Business"]}, {"wrapperType": "track", "kind": "podcast", "collectionId": 1834995819, "trackId": 1834995819, "artistName": "Niagara Frontier Radio Reading Service", "collectionName": "NFRRS Magazines & Periodicals", "trackName": "NFRRS Magazines & Periodicals", "collectionCensoredName": "NFRRS Magazines & Periodicals", "trackCensoredName": "NFRRS Magazines & Periodicals", "collectionViewUrl": "https://podcasts.apple.com/id/podcast/nfrrs-magazines-periodicals/id1834995819?uo=4", "feedUrl": "https://nfrrs-rss.streamguys1.com/nfrrs/archive-mags-apple-podcasts.xml", "trackViewUrl": "https://podcasts.apple.com/id/podcast/nfrrs-magazines-periodicals/id1834995819?uo=4", "artworkUrl30": "https://is1-ssl.mzstatic.com/image/thumb/Podcasts221/v4/6c/f8/68/6cf86808-7287-0788-7d89-d4817eb53bf7/mza_3430228559749322418.jpg/30x30bb.jpg", "artworkUrl60": "https://is1-ssl.mzstatic.com/image/thumb/Podcasts221/v4/6c/f8/68/6cf86808-7287-0788-7d89-d4817eb53bf7/mza_3430228559749322418.jpg/60x60bb.jpg", "artworkUrl100": "https://is1-ssl.mzstatic.com/image/thumb/Podcasts221/v4/6c/f8/68/6cf86808-7287-0788-7d89-d4817eb53bf7/mza_3430228559749322418.jpg/100x100bb.jpg", "collectionPrice": 0.0, "trackPrice": 0.0, "collectionHdPrice": 0, "releaseDate": "2026-07-12T02:00:00Z", "collectionExplicitness": "notExplicit", "trackExplicitness": "cleaned", "trackCount": 26, "trackTimeMillis": 3603, "country": "IDN", "currency": "IDR", "primaryGenreName": "Non-Profit", "contentAdvisoryRating": "Clean", "artworkUrl600": "https://is1-ssl.mzstatic.com/image/thumb/Podcasts221/v4/6c/f8/68/6cf86808-7287-0788-7d89-d4817eb53bf7/mza_3430228559749322418.jpg/600x600bb.jpg", "genreIds": ["1494", "26", "1321", "1512"], "genres": ["Non-Profit", "Podcasts", "Business", "Health & Fitness"]}, {"wrapperType": "track", "kind": "podcast", "collectionId": 1588243181, "trackId": 1588243181, "artistName": "Embassy of Colombia in Indonesia", "collectionName": "Colombia in Indonesia", "trackName": "Colombia in Indonesia", "collectionCensoredName": "Colombia in Indonesia", "trackCensoredName": "Colombia in Indonesia", "collectionViewUrl": "https://podcasts.apple.com/id/podcast/colombia-in-indonesia/id1588243181?uo=4", "feedUrl": "https://anchor.fm/s/6a7f2d0c/podcast/rss", "trackViewUrl": "https://podcasts.apple.com/id/podcast/colombia-in-indonesia/id1588243181?uo=4", "artworkUrl30": "https://is1-ssl.mzstatic.com/image/thumb/Podcasts122/v4/d1/0e/0f/d10e0fa4-af87-cc9b-78c5-1e415ec89bb2/mza_7633680503220008457.jpg/30x30bb.jpg", "artworkUrl60": "https://is1-ssl.mzstatic.com/image/thumb/Podcasts122/v4/d1/0e/0f/d10e0fa4-af87-cc9b-78c5-1e415ec89bb2/mza_7633680503220008457.jpg/60x60bb.jpg", "artworkUrl100": "https://is1-ssl.mzstatic.com/image/thumb/Podcasts122/v4/d1/0e/0f/d10e0fa4-af87-cc9b-78c5-1e415ec89bb2/mza_7633680503220008457.jpg/100x100bb.jpg", "collectionPrice": 0.0, "trackPrice": 0.0, "collectionHdPrice": 0, "releaseDate": "2023-05-30T12:30:00Z", "collectionExplicitness": "notExplicit", "trackExplicitness": "cleaned", "trackCount": 33, "trackTimeMillis": 372, "country": "IDN", "currency": "IDR", "primaryGenreName": "Society & Culture", "contentAdvisoryRating": "Clean", "artworkUrl600": "https://is1-ssl.mzstatic.com/image/thumb/Podcasts122/v4/d1/0e/0f/d10e0fa4-af87-cc9b-78c5-1e415ec89bb2/mza_7633680503220008457.jpg/600x600bb.jpg", "genreIds": ["1324", "26"], "genres": ["Society & Culture", "Podcasts"]}, {"wrapperType": "track", "kind": "podcast", "collectionId": 1358757469, "trackId": 1358757469, "artistName": "Radio Eye", "collectionName": "Smithsonian Magazine", "trackName": "Smithsonian Magazine", "collectionCensoredName": "Smithsonian Magazine", "trackCensoredName": "Smithsonian Magazine", "collectionViewUrl": "https://podcasts.apple.com/id/podcast/smithsonian-magazine/id1358757469?uo=4", "feedUrl": "https://www.spreaker.com/show/2827639/episodes/feed", "trackViewUrl": "https://podcasts.apple.com/id/podcast/smithsonian-magazine/id1358757469?uo=4", "artworkUrl30": "https://is1-ssl.mzstatic.com/image/thumb/Podcasts125/v4/f8/a6/04/f8a604ae-a507-beeb-32f0-36caf9358b9b/mza_9296829280210722165.jpg/30x30bb.jpg", "artworkUrl60": "https://is1-ssl.mzstatic.com/image/thumb/Podcasts125/v4/f8/a6/04/f8a604ae-a507-beeb-32f0-36caf9358b9b/mza_9296829280210722165.jpg/60x60bb.jpg", "artworkUrl100": "https://is1-ssl.mzstatic.com/image/thumb/Podcasts125/v4/f8/a6/04/f8a604ae-a507-beeb-32f0-36caf9358b9b/mza_9296829280210722165.jpg/100x100bb.jpg", "collectionPrice": 0.0, "trackPrice": 0.0, "collectionHdPrice": 0, "releaseDate": "2026-07-02T16:16:00Z", "collectionExplicitness": "notExplicit", "trackExplicitness": "cleaned", "trackCount": 73, "trackTimeMillis": 1690, "country": "IDN", "currency": "IDR", "primaryGenreName": "Science", "contentAdvisoryRating": "Clean", "artworkUrl600": "https://is1-ssl.mzstatic.com/image/thumb/Podcasts125/v4/f8/a6/04/f8a604ae-a507-beeb-32f0-36caf9358b9b/mza_9296829280210722165.jpg/600x600bb.jpg", "genreIds": ["1533", "26"], "genres": ["Science", "Podcasts"]}, {"wrapperType": "track", "kind": "podcast", "collectionId": 1635012536, "trackId": 1635012536, "artistName": "Let's Talk Hoya", "collectionName": "Let’s Talk Hoya", "trackName": "Let’s Talk Hoya", "collectionCensoredName": "Let’s Talk Hoya", "trackCensoredName": "Let’s Talk Hoya", "collectionViewUrl": "https://podcasts.apple.com/id/podcast/lets-talk-hoya/id1635012536?uo=4", "feedUrl": "https://feeds.redcircle.com/843d030e-91a7-44e3-8805-c9d871c329d4", "trackViewUrl": "https://podcasts.apple.com/id/podcast/lets-talk-hoya/id1635012536?uo=4", "artworkUrl30": "https://is1-ssl.mzstatic.com/image/thumb/Podcasts123/v4/9c/20/32/9c203297-bb0c-30f2-de93-b24dfdca4176/mza_14232881611718707706.jpg/30x30bb.jpg", "artworkUrl60": "https://is1-ssl.mzstatic.com/image/thumb/Podcasts123/v4/9c/20/32/9c203297-bb0c-30f2-de93-b24dfdca4176/mza_14232881611718707706.jpg/60x60bb.jpg", "artworkUrl100": "https://is1-ssl.mzstatic.com/image/thumb/Podcasts123/v4/9c/20/32/9c203297-bb0c-30f2-de93-b24dfdca4176/mza_14232881611718707706.jpg/100x100bb.jpg", "collectionPrice": 0.0, "trackPrice": 0.0, "collectionHdPrice": 0, "releaseDate": "2025-11-27T12:00:00Z", "collectionExplicitness": "notExplicit", "trackExplicitness": "cleaned", "trackCount": 77, "trackTimeMillis": 3766, "country": "IDN", "currency": "IDR", "primaryGenreName": "Home & Garden", "contentAdvisoryRating": "Clean", "artworkUrl600": "https://is1-ssl.mzstatic.com/image/thumb/Podcasts123/v4/9c/20/32/9c203297-bb0c-30f2-de93-b24dfdca4176/mza_14232881611718707706.jpg/600x600bb.jpg", "genreIds": ["1508", "26", "1502"], "genres": ["Home & Garden", "Podcasts", "Leisure"]}, {"wrapperType": "track", "kind": "podcast", "collectionId": 1440020656, "trackId": 1440020656, "artistName": "Rob Tyson", "collectionName": "Dig Deep", "trackName": "Dig Deep", "collectionCensoredName": "Dig Deep", "trackCensoredName": "Dig Deep", "collectionViewUrl": "https://podcasts.apple.com/id/podcast/dig-deep/id1440020656?uo=4", "feedUrl": "https://feeds.megaphone.fm/USVL2635439643", "trackViewUrl": "https://podcasts.apple.com/id/podcast/dig-deep/id1440020656?uo=4", "artworkUrl30": "https://is1-ssl.mzstatic.com/image/thumb/Podcasts221/v4/77/e5/79/77e5794b-dba0-9cfe-6546-0d06bfdb8b3e/mza_3171331539526821460.jpg/30x30bb.jpg", "artworkUrl60": "https://is1-ssl.mzstatic.com/image/thumb/Podcasts221/v4/77/e5/79/77e5794b-dba0-9cfe-6546-0d06bfdb8b3e/mza_3171331539526821460.jpg/60x60bb.jpg", "artworkUrl100": "https://is1-ssl.mzstatic.com/image/thumb/Podcasts221/v4/77/e5/79/77e5794b-dba0-9cfe-6546-0d06bfdb8b3e/mza_3171331539526821460.jpg/100x100bb.jpg", "collectionPrice": 0.0, "trackPrice": 0.0, "collectionHdPrice": 0, "releaseDate": "2026-07-09T00:00:00Z", "collectionExplicitness": "notExplicit", "trackExplicitness": "cleaned", "trackCount": 638, "trackTimeMillis": 1179, "country": "IDN", "currency": "IDR", "primaryGenreName": "Careers", "contentAdvisoryRating": "Clean", "artworkUrl600": "https://is1-ssl.mzstatic.com/image/thumb/Podcasts221/v4/77/e5/79/77e5794b-dba0-9cfe-6546-0d06bfdb8b3e/mza_3171331539526821460.jpg/600x600bb.jpg", "genreIds": ["1410", "26", "1321", "1412"], "genres": ["Careers", "Podcasts", "Business", "Investing"]}, {"wrapperType": "track", "kind": "podcast", "collectionId": 1789980879, "trackId": 1789980879, "artistName": "Environment+Energy Leader", "collectionName": "Sustainability Soundbites from E+E Leader", "trackName": "Sustainability Soundbites from E+E Leader", "collectionCensoredName": "Sustainability Soundbites from E+E Leader", "trackCensoredName": "Sustainability Soundbites from E+E Leader", "collectionViewUrl": "https://podcasts.apple.com/id/podcast/sustainability-soundbites-from-e-e-leader/id1789980879?uo=4", "feedUrl": "https://rss.buzzsprout.com/2441376.rss", "trackViewUrl": "https://podcasts.apple.com/id/podcast/sustainability-soundbites-from-e-e-leader/id1789980879?uo=4", "artworkUrl30": "https://is1-ssl.mzstatic.com/image/thumb/Podcasts221/v4/f4/05/a5/f405a50f-a821-3481-2e6d-c5e0c7c7000e/mza_3059971966696555898.jpg/30x30bb.jpg", "artworkUrl60": "https://is1-ssl.mzstatic.com/image/thumb/Podcasts221/v4/f4/05/a5/f405a50f-a821-3481-2e6d-c5e0c7c7000e/mza_3059971966696555898.jpg/60x60bb.jpg", "artworkUrl100": "https://is1-ssl.mzstatic.com/image/thumb/Podcasts221/v4/f4/05/a5/f405a50f-a821-3481-2e6d-c5e0c7c7000e/mza_3059971966696555898.jpg/100x100bb.jpg", "collectionPrice": 0.0, "trackPrice": 0.0, "collectionHdPrice": 0, "releaseDate": "2026-07-10T22:00:00Z", "collectionExplicitness": "notExplicit", "trackExplicitness": "cleaned", "trackCount": 2000, "trackTimeMillis": 226, "country": "IDN", "currency": "IDR", "primaryGenreName": "News", "contentAdvisoryRating": "Clean", "artworkUrl600": "https://is1-ssl.mzstatic.com/image/thumb/Podcasts221/v4/f4/05/a5/f405a50f-a821-3481-2e6d-c5e0c7c7000e/mza_3059971966696555898.jpg/600x600bb.jpg", "genreIds": ["1489", "26"], "genres": ["News", "Podcasts"]}, {"wrapperType": "track", "kind": "podcast", "collectionId": 1831470265, "trackId": 1831470265, "artistName": "ThinkLandscape", "collectionName": "TalkLandscape", "trackName": "TalkLandscape", "collectionCensoredName": "TalkLandscape", "trackCensoredName": "TalkLandscape", "collectionViewUrl": "https://podcasts.apple.com/id/podcast/talklandscape/id1831470265?uo=4", "feedUrl": "https://feeds.redcircle.com/2dbf898c-8ea1-4e40-9e8e-09142a7ae9ce", "trackViewUrl": "https://podcasts.apple.com/id/podcast/talklandscape/id1831470265?uo=4", "artworkUrl30": "https://is1-ssl.mzstatic.com/image/thumb/Podcasts221/v4/c6/01/b5/c601b596-edbf-5641-aafd-09773cbaab4f/mza_16143164717468291682.jpg/30x30bb.jpg", "artworkUrl60": "https://is1-ssl.mzstatic.com/image/thumb/Podcasts221/v4/c6/01/b5/c601b596-edbf-5641-aafd-09773cbaab4f/mza_16143164717468291682.jpg/60x60bb.jpg", "artworkUrl100": "https://is1-ssl.mzstatic.com/image/thumb/Podcasts221/v4/c6/01/b5/c601b596-edbf-5641-aafd-09773cbaab4f/mza_16143164717468291682.jpg/100x100bb.jpg", "collectionPrice": 0.0, "trackPrice": 0.0, "collectionHdPrice": 0, "releaseDate": "2026-06-17T12:05:00Z", "collectionExplicitness": "notExplicit", "trackExplicitness": "cleaned", "trackCount": 11, "trackTimeMillis": 2025, "country": "IDN", "currency": "IDR", "primaryGenreName": "Science", "contentAdvisoryRating": "Clean", "artworkUrl600": "https://is1-ssl.mzstatic.com/image/thumb/Podcasts221/v4/c6/01/b5/c601b596-edbf-5641-aafd-09773cbaab4f/mza_16143164717468291682.jpg/600x600bb.jpg", "genreIds": ["1533", "26", "1489"], "genres": ["Science", "Podcasts", "News"]}, {"wrapperType": "track", "kind": "podcast", "collectionId": 1697300598, "trackId": 1697300598, "artistName": "Daisy Barrett & Tess McKelliget", "collectionName": "Trainer Talks and Tails", "trackName": "Trainer Talks and Tails", "collectionCensoredName": "Trainer Talks and Tails", "trackCensoredName": "Trainer Talks and Tails", "collectionViewUrl": "https://podcasts.apple.com/id/podcast/trainer-talks-and-tails/id1697300598?uo=4", "feedUrl": "https://media.rss.com/trainertalksandtails/feed.xml", "trackViewUrl": "https://podcasts.apple.com/id/podcast/trainer-talks-and-tails/id1697300598?uo=4", "artworkUrl30": "https://is1-ssl.mzstatic.com/image/thumb/Podcasts116/v4/dc/dc/8c/dcdc8c2e-a68e-6664-791c-bf2eb223e8a0/mza_2502834712896120213.jpg/30x30bb.jpg", "artworkUrl60": "https://is1-ssl.mzstatic.com/image/thumb/Podcasts116/v4/dc/dc/8c/dcdc8c2e-a68e-6664-791c-bf2eb223e8a0/mza_2502834712896120213.jpg/60x60bb.jpg", "artworkUrl100": "https://is1-ssl.mzstatic.com/image/thumb/Podcasts116/v4/dc/dc/8c/dcdc8c2e-a68e-6664-791c-bf2eb223e8a0/mza_2502834712896120213.jpg/100x100bb.jpg", "collectionPrice": 0.0, "trackPrice": 0.0, "collectionHdPrice": 0, "releaseDate": "2024-12-11T12:10:00Z", "collectionExplicitness": "notExplicit", "trackExplicitness": "cleaned", "trackCount": 60, "trackTimeMillis": 2734, "country": "IDN", "currency": "IDR", "primaryGenreName": "Pets & Animals", "contentAdvisoryRating": "Clean", "artworkUrl600": "https://is1-ssl.mzstatic.com/image/thumb/Podcasts116/v4/dc/dc/8c/dcdc8c2e-a68e-6664-791c-bf2eb223e8a0/mza_2502834712896120213.jpg/600x600bb.jpg", "genreIds": ["1522", "26", "1305"], "genres": ["Pets & Animals", "Podcasts", "Kids & Family"]}, {"wrapperType": "track", "kind": "podcast", "collectionId": 1553199216, "trackId": 1553199216, "artistName": "On The Level Media", "collectionName": "Reformasi Dispatch", "trackName": "Reformasi Dispatch", "collectionCensoredName": "Reformasi Dispatch", "trackCensoredName": "Reformasi Dispatch", "collectionViewUrl": "https://podcasts.apple.com/id/podcast/reformasi-dispatch/id1553199216?uo=4", "feedUrl": "https://rss.buzzsprout.com/1679743.rss", "trackViewUrl": "https://podcasts.apple.com/id/podcast/reformasi-dispatch/id1553199216?uo=4", "artworkUrl30": "https://is1-ssl.mzstatic.com/image/thumb/Podcasts211/v4/2b/b5/ed/2bb5ed91-9eb9-7b15-da92-a9953889427e/mza_13973218662085803887.jpg/30x30bb.jpg", "artworkUrl60": "https://is1-ssl.mzstatic.com/image/thumb/Podcasts211/v4/2b/b5/ed/2bb5ed91-9eb9-7b15-da92-a9953889427e/mza_13973218662085803887.jpg/60x60bb.jpg", "artworkUrl100": "https://is1-ssl.mzstatic.com/image/thumb/Podcasts211/v4/2b/b5/ed/2bb5ed91-9eb9-7b15-da92-a9953889427e/mza_13973218662085803887.jpg/100x100bb.jpg", "collectionPrice": 0.0, "trackPrice": 0.0, "collectionHdPrice": 0, "releaseDate": "2026-07-12T02:00:00Z", "collectionExplicitness": "notExplicit", "trackExplicitness": "cleaned", "trackCount": 208, "trackTimeMillis": 3144, "country": "IDN", "currency": "IDR", "primaryGenreName": "Politics", "contentAdvisoryRating": "Clean", "artworkUrl600": "https://is1-ssl.mzstatic.com/image/thumb/Podcasts211/v4/2b/b5/ed/2bb5ed91-9eb9-7b15-da92-a9953889427e/mza_13973218662085803887.jpg/600x600bb.jpg", "genreIds": ["1527", "26", "1489", "1530"], "genres": ["Politics", "Podcasts", "News", "News Commentary"]}, {"wrapperType": "track", "kind": "podcast", "collectionId": 1617855526, "trackId": 1617855526, "artistName": "Hugo Gonzalez", "collectionName": "Foolish House", "trackName": "Foolish House", "collectionCensoredName": "Foolish House", "trackCensoredName": "Foolish House", "collectionViewUrl": "https://podcasts.apple.com/id/podcast/foolish-house/id1617855526?uo=4", "feedUrl": "https://anchor.fm/s/3572de10/podcast/rss", "trackViewUrl": "https://podcasts.apple.com/id/podcast/foolish-house/id1617855526?uo=4", "artworkUrl30": "https://is1-ssl.mzstatic.com/image/thumb/Podcasts122/v4/03/7c/cb/037ccb3a-d3fc-fe2c-fcff-a8ce378deea2/mza_10983869765214015595.jpg/30x30bb.jpg", "artworkUrl60": "https://is1-ssl.mzstatic.com/image/thumb/Podcasts122/v4/03/7c/cb/037ccb3a-d3fc-fe2c-fcff-a8ce378deea2/mza_10983869765214015595.jpg/60x60bb.jpg", "artworkUrl100": "https://is1-ssl.mzstatic.com/image/thumb/Podcasts122/v4/03/7c/cb/037ccb3a-d3fc-fe2c-fcff-a8ce378deea2/mza_10983869765214015595.jpg/100x100bb.jpg", "collectionPrice": 0.0, "trackPrice": 0.0, "collectionHdPrice": 0, "releaseDate": "2026-06-22T23:59:00Z", "collectionExplicitness": "notExplicit", "trackExplicitness": "explicit", "trackCount": 111, "trackTimeMillis": 3535, "country": "IDN", "currency": "IDR", "primaryGenreName": "Comedy", "contentAdvisoryRating": "Explicit", "artworkUrl600": "https://is1-ssl.mzstatic.com/image/thumb/Podcasts122/v4/03/7c/cb/037ccb3a-d3fc-fe2c-fcff-a8ce378deea2/mza_10983869765214015595.jpg/600x600bb.jpg", "genreIds": ["1303", "26"], "genres": ["Comedy", "Podcasts"]}, {"wrapperType": "track", "kind": "podcast", "collectionId": 1800562973, "trackId": 1800562973, "artistName": "Ken Hudnall", "collectionName": "The Ken Hudnall Show", "trackName": "The Ken Hudnall Show", "collectionCensoredName": "The Ken Hudnall Show", "trackCensoredName": "The Ken Hudnall Show", "collectionViewUrl": "https://podcasts.apple.com/id/podcast/the-ken-hudnall-show/id1800562973?uo=4", "feedUrl": "https://feed.podbean.com/Kenhudnall0/feed.xml", "trackViewUrl": "https://podcasts.apple.com/id/podcast/the-ken-hudnall-show/id1800562973?uo=4", "artworkUrl30": "https://is1-ssl.mzstatic.com/image/thumb/Podcasts211/v4/ce/a2/7e/cea27e5d-16cc-cbfa-6a6e-c2b2772f3f2e/mza_12704718331622019811.jpg/30x30bb.jpg", "artworkUrl60": "https://is1-ssl.mzstatic.com/image/thumb/Podcasts211/v4/ce/a2/7e/cea27e5d-16cc-cbfa-6a6e-c2b2772f3f2e/mza_12704718331622019811.jpg/60x60bb.jpg", "artworkUrl100": "https://is1-ssl.mzstatic.com/image/thumb/Podcasts211/v4/ce/a2/7e/cea27e5d-16cc-cbfa-6a6e-c2b2772f3f2e/mza_12704718331622019811.jpg/100x100bb.jpg", "collectionPrice": 0.0, "trackPrice": 0.0, "collectionHdPrice": 0, "releaseDate": "2026-07-09T20:19:00Z", "collectionExplicitness": "notExplicit", "trackExplicitness": "cleaned", "trackCount": 99, "trackTimeMillis": 3486, "country": "IDN", "currency": "IDR", "primaryGenreName": "News", "contentAdvisoryRating": "Clean", "artworkUrl600": "https://is1-ssl.mzstatic.com/image/thumb/Podcasts211/v4/ce/a2/7e/cea27e5d-16cc-cbfa-6a6e-c2b2772f3f2e/mza_12704718331622019811.jpg/600x600bb.jpg", "genreIds": ["1489", "26", "1314"], "genres": ["News", "Podcasts", "Religion & Spirituality"]}, {"wrapperType": "track", "kind": "podcast", "collectionId": 1453453787, "trackId": 1453453787, "artistName": "Ken Hudnall", "collectionName": "The Ken Hudnall Show", "trackName": "The Ken Hudnall Show", "collectionCensoredName": "The Ken Hudnall Show", "trackCensoredName": "The Ken Hudnall Show", "collectionViewUrl": "https://podcasts.apple.com/id/podcast/the-ken-hudnall-show/id1453453787?uo=4", "feedUrl": "https://feed.podbean.com/Kenhudnall0/feed.xml", "trackViewUrl": "https://podcasts.apple.com/id/podcast/the-ken-hudnall-show/id1453453787?uo=4", "artworkUrl30": "https://is1-ssl.mzstatic.com/image/thumb/Podcasts125/v4/6d/e0/3b/6de03bf0-a860-57e3-8837-022ff670ed7b/mza_2306973610256472742.jpg/30x30bb.jpg", "artworkUrl60": "https://is1-ssl.mzstatic.com/image/thumb/Podcasts125/v4/6d/e0/3b/6de03bf0-a860-57e3-8837-022ff670ed7b/mza_2306973610256472742.jpg/60x60bb.jpg", "artworkUrl100": "https://is1-ssl.mzstatic.com/image/thumb/Podcasts125/v4/6d/e0/3b/6de03bf0-a860-57e3-8837-022ff670ed7b/mza_2306973610256472742.jpg/100x100bb.jpg", "collectionPrice": 0.0, "trackPrice": 0.0, "collectionHdPrice": 0, "releaseDate": "2026-07-09T20:19:00Z", "collectionExplicitness": "notExplicit", "trackExplicitness": "cleaned", "trackCount": 99, "trackTimeMillis": 3486, "country": "IDN", "currency": "IDR", "primaryGenreName": "News", "contentAdvisoryRating": "Clean", "artworkUrl600": "https://is1-ssl.mzstatic.com/image/thumb/Podcasts125/v4/6d/e0/3b/6de03bf0-a860-57e3-8837-022ff670ed7b/mza_2306973610256472742.jpg/600x600bb.jpg", "genreIds": ["1489", "26", "1314"], "genres": ["News", "Podcasts", "Religion & Spirituality"]}, {"wrapperType": "track", "kind": "podcast", "collectionId": 1305526998, "trackId": 1305526998, "artistName": "Brendan Carmel and Mark Simpson", "collectionName": "Veterinary Podcast by the VetGurus", "trackName": "Veterinary Podcast by the VetGurus", "collectionCensoredName": "Veterinary Podcast by the VetGurus", "trackCensoredName": "Veterinary Podcast by the VetGurus", "collectionViewUrl": "https://podcasts.apple.com/id/podcast/veterinary-podcast-by-the-vetgurus/id1305526998?uo=4", "feedUrl": "http://vetpodcast.blubrry.net/feed/podcast/", "trackViewUrl": "https://podcasts.apple.com/id/podcast/veterinary-podcast-by-the-vetgurus/id1305526998?uo=4", "artworkUrl30": "https://is1-ssl.mzstatic.com/image/thumb/Podcasts115/v4/d8/28/2f/d8282fc9-eea6-66c7-2fab-58da7406995a/mza_1129639948212528293.png/30x30bb.jpg", "artworkUrl60": "https://is1-ssl.mzstatic.com/image/thumb/Podcasts115/v4/d8/28/2f/d8282fc9-eea6-66c7-2fab-58da7406995a/mza_1129639948212528293.png/60x60bb.jpg", "artworkUrl100": "https://is1-ssl.mzstatic.com/image/thumb/Podcasts115/v4/d8/28/2f/d8282fc9-eea6-66c7-2fab-58da7406995a/mza_1129639948212528293.png/100x100bb.jpg", "collectionPrice": 0.0, "trackPrice": 0.0, "collectionHdPrice": 0, "releaseDate": "2026-07-01T16:25:00Z", "collectionExplicitness": "notExplicit", "trackExplicitness": "cleaned", "trackCount": 460, "trackTimeMillis": 1378, "country": "IDN", "currency": "IDR", "primaryGenreName": "Natural Sciences", "contentAdvisoryRating": "Clean", "artworkUrl600": "https://is1-ssl.mzstatic.com/image/thumb/Podcasts115/v4/d8/28/2f/d8282fc9-eea6-66c7-2fab-58da7406995a/mza_1129639948212528293.png/600x600bb.jpg", "genreIds": ["1534", "26", "1533", "1512", "1518"], "genres": ["Natural Sciences", "Podcasts", "Science", "Health & Fitness", "Medicine"]}, {"wrapperType": "track", "kind": "podcast", "collectionId": 1670791799, "trackId": 1670791799, "artistName": "Ubud Writers & Readers Festival", "collectionName": "Ubud Writers & Readers Festival Podcast", "trackName": "Ubud Writers & Readers Festival Podcast", "collectionCensoredName": "Ubud Writers & Readers Festival Podcast", "trackCensoredName": "Ubud Writers & Readers Festival Podcast", "collectionViewUrl": "https://podcasts.apple.com/id/podcast/ubud-writers-readers-festival-podcast/id1670791799?uo=4", "feedUrl": "https://feeds.simplecast.com/eUhy4nqz", "trackViewUrl": "https://podcasts.apple.com/id/podcast/ubud-writers-readers-festival-podcast/id1670791799?uo=4", "artworkUrl30": "https://is1-ssl.mzstatic.com/image/thumb/Podcasts126/v4/49/1e/2d/491e2d2b-7f0e-cfc2-2d7c-271d62e867b7/mza_16491484423874585321.jpg/30x30bb.jpg", "artworkUrl60": "https://is1-ssl.mzstatic.com/image/thumb/Podcasts126/v4/49/1e/2d/491e2d2b-7f0e-cfc2-2d7c-271d62e867b7/mza_16491484423874585321.jpg/60x60bb.jpg", "artworkUrl100": "https://is1-ssl.mzstatic.com/image/thumb/Podcasts126/v4/49/1e/2d/491e2d2b-7f0e-cfc2-2d7c-271d62e867b7/mza_16491484423874585321.jpg/100x100bb.jpg", "collectionPrice": 0.0, "trackPrice": 0.0, "collectionHdPrice": 0, "releaseDate": "2026-03-16T01:00:00Z", "collectionExplicitness": "notExplicit", "trackExplicitness": "cleaned", "trackCount": 149, "trackTimeMillis": 3672, "country": "IDN", "currency": "IDR", "primaryGenreName": "Books", "contentAdvisoryRating": "Clean", "artworkUrl600": "https://is1-ssl.mzstatic.com/image/thumb/Podcasts126/v4/49/1e/2d/491e2d2b-7f0e-cfc2-2d7c-271d62e867b7/mza_16491484423874585321.jpg/600x600bb.jpg", "genreIds": ["1482", "26", "1301", "1304", "1499"], "genres": ["Books", "Podcasts", "Arts", "Education", "How To"]}]}